{"user": "011f4a78023ece4cdd00d9a53707950972f546ac", "user_type": "russian_bot", "data": {"directed": true, "multigraph": false, "graph": {}, "nodes": [{"post_data": [{"created_at": 1523368805.0, "distinguished": "admin", "type": "submission", "score": 594, "id": "8b7ryg"}], "id": "u_reddit"}, {"post_data": [{"created_at": 1463303078.0, "distinguished": null, "type": "submission", "score": 9, "id": "4jfdec"}], "id": "HillaryForPrison2016"}, {"post_data": [{"created_at": 1456054919.0, "distinguished": null, "type": "submission", "score": 13, "id": "46uygh"}], "id": "funny"}], "links": [{"time_delta": [60065727.0], "count": 1, "source": "HillaryForPrison2016", "target": "u_reddit"}, {"time_delta": [7248159.0], "count": 1, "source": "funny", "target": "HillaryForPrison2016"}]}}