{"user": "1e96ad08f4477371d8783f8a305a754717b14a62", "user_type": "random_user", "data": {"directed": true, "multigraph": false, "graph": {}, "nodes": [{"post_data": [{"created_at": 1555363157.0, "distinguished": null, "type": "comment", "score": 4, "id": "ekyyttz"}], "id": "pics"}, {"post_data": [{"created_at": 1555256766.0, "distinguished": null, "type": "comment", "score": 5, "id": "ekvk1v7"}, {"created_at": 1555002827.0, "distinguished": null, "type": "comment", "score": 2, "id": "ekn8a7n"}, {"created_at": 1554999395.0, "distinguished": null, "type": "comment", "score": 9, "id": "ekn2wqj"}, {"created_at": 1554979679.0, "distinguished": null, "type": "comment", "score": 1, "id": "ekmbt1h"}, {"created_at": 1554938395.0, "distinguished": null, "type": "comment", "score": 7, "id": "ekl6wes"}, {"created_at": 1554754766.0, "distinguished": null, "type": "comment", "score": 0, "id": "ekeyayj"}, {"created_at": 1554659840.0, "distinguished": null, "type": "comment", "score": 3, "id": "ekbtdci"}, {"created_at": 1554655913.0, "distinguished": null, "type": "comment", "score": 1, "id": "ekbnvhb"}, {"created_at": 1554496906.0, "distinguished": null, "type": "comment", "score": 2, "id": "ek7cfd8"}, {"created_at": 1554408006.0, "distinguished": null, "type": "comment", "score": 4, "id": "ek4jt4b"}, {"created_at": 1554404986.0, "distinguished": null, "type": "comment", "score": 1, "id": "ek4f3ek"}, {"created_at": 1554400234.0, "distinguished": null, "type": "comment", "score": 4, "id": "ek47yko"}, {"created_at": 1554398667.0, "distinguished": null, "type": "comment", "score": 6, "id": "ek45mx0"}, {"created_at": 1554381596.0, "distinguished": null, "type": "comment", "score": 1, "id": "ek3hpuj"}, {"created_at": 1554306809.0, "distinguished": null, "type": "comment", "score": 3, "id": "ek13qx1"}, {"created_at": 1554234735.0, "distinguished": null, "type": "comment", "score": 1, "id": "ejyzbr7"}, {"created_at": 1554233745.0, "distinguished": null, "type": "comment", "score": 2, "id": "ejyxrzb"}, {"created_at": 1554230680.0, "distinguished": null, "type": "comment", "score": 2, "id": "ejysz0t"}, {"created_at": 1554226782.0, "distinguished": null, "type": "comment", "score": 5, "id": "ejymx21"}, {"created_at": 1554139607.0, "distinguished": null, "type": "comment", "score": 17, "id": "ejvxw0j"}, {"created_at": 1554139562.0, "distinguished": null, "type": "comment", "score": 5, "id": "ejvxtds"}, {"created_at": 1554050603.0, "distinguished": null, "type": "comment", "score": 1, "id": "ejtb174"}, {"created_at": 1554028583.0, "distinguished": null, "type": "comment", "score": 3, "id": "ejsons0"}, {"created_at": 1554024496.0, "distinguished": null, "type": "comment", "score": -4, "id": "ejsmgsa"}, {"created_at": 1553628220.0, "distinguished": null, "type": "comment", "score": 2, "id": "ejfukp4"}, {"created_at": 1553415484.0, "distinguished": null, "type": "comment", "score": 1, "id": "ej957b3"}, {"created_at": 1553387313.0, "distinguished": null, "type": "comment", "score": 2, "id": "ej8fs4d"}, {"created_at": 1553355252.0, "distinguished": null, "type": "comment", "score": 1, "id": "ej77lah"}, {"created_at": 1553278208.0, "distinguished": null, "type": "comment", "score": 6, "id": "ej4wij4"}, {"created_at": 1553196778.0, "distinguished": null, "type": "comment", "score": 5, "id": "ej2av1m"}], "id": "GhostRecon"}, {"post_data": [{"created_at": 1555256304.0, "distinguished": null, "type": "comment", "score": 2, "id": "ekvjg45"}, {"created_at": 1555244408.0, "distinguished": null, "type": "comment", "score": 1, "id": "ekv6s05"}, {"created_at": 1555013925.0, "distinguished": null, "type": "comment", "score": 2, "id": "eknqa4t"}], "id": "arma"}, {"post_data": [{"created_at": 1555244099.0, "distinguished": null, "type": "comment", "score": 1, "id": "ekv6j7z"}, {"created_at": 1554793668.0, "distinguished": null, "type": "comment", "score": 7, "id": "ekgcjsd"}, {"created_at": 1551487439.0, "distinguished": null, "type": "comment", "score": -2, "id": "ehlfs5p"}, {"created_at": 1551480910.0, "distinguished": null, "type": "comment", "score": 1, "id": "ehl7kmj"}], "id": "linuxquestions"}, {"post_data": [{"created_at": 1555186803.0, "distinguished": null, "type": "comment", "score": 2, "id": "ektkwmj"}, {"created_at": 1555047438.0, "distinguished": null, "type": "comment", "score": 1, "id": "ekoxbov"}, {"created_at": 1554968756.0, "distinguished": null, "type": "comment", "score": 4, "id": "ekm357z"}, {"created_at": 1554828712.0, "distinguished": null, "type": "comment", "score": 1, "id": "ekhc73z"}, {"created_at": 1554794043.0, "distinguished": null, "type": "comment", "score": 9, "id": "ekgcrsb"}, {"created_at": 1554629957.0, "distinguished": null, "type": "comment", "score": 6, "id": "ekayz19"}, {"created_at": 1554496715.0, "distinguished": null, "type": "comment", "score": 15, "id": "ek7c4je"}, {"created_at": 1554376229.0, "distinguished": null, "type": "comment", "score": 1, "id": "ek3cndz"}, {"created_at": 1550848396.0, "distinguished": null, "type": "comment", "score": 1, "id": "eh180r0"}, {"created_at": 1550816815.0, "distinguished": null, "type": "comment", "score": 1, "id": "eh0iwgs"}, {"created_at": 1550787249.0, "distinguished": null, "type": "comment", "score": 1, "id": "egzimnc"}, {"created_at": 1550770706.0, "distinguished": null, "type": "comment", "score": 2, "id": "egytsq0"}, {"created_at": 1550770528.0, "distinguished": null, "type": "comment", "score": 1, "id": "egytj95"}, {"created_at": 1550770021.0, "distinguished": null, "type": "comment", "score": 2, "id": "egysroo"}, {"created_at": 1550763040.0, "distinguished": null, "type": "comment", "score": 3, "id": "egyimdw"}, {"created_at": 1550613620.0, "distinguished": null, "type": "comment", "score": 1, "id": "egu0mgw"}, {"created_at": 1550605890.0, "distinguished": null, "type": "comment", "score": 2, "id": "egtoytw"}, {"created_at": 1550516556.0, "distinguished": null, "type": "comment", "score": 1, "id": "egqw6ba"}, {"created_at": 1550434289.0, "distinguished": null, "type": "comment", "score": 8, "id": "egojg1n"}, {"created_at": 1550411767.0, "distinguished": null, "type": "comment", "score": 1, "id": "egnt6q2"}, {"created_at": 1550349305.0, "distinguished": null, "type": "comment", "score": 1, "id": "egm9k96"}, {"created_at": 1550344997.0, "distinguished": null, "type": "comment", "score": 2, "id": "egm497k"}, {"created_at": 1550333558.0, "distinguished": null, "type": "comment", "score": 3, "id": "eglq9aa"}, {"created_at": 1550270928.0, "distinguished": null, "type": "comment", "score": 1, "id": "egk9a82"}, {"created_at": 1550143030.0, "distinguished": null, "type": "comment", "score": 1, "id": "egg7zh1"}, {"created_at": 1550099333.0, "distinguished": null, "type": "comment", "score": 1, "id": "egf2l1e"}, {"created_at": 1550061391.0, "distinguished": null, "type": "comment", "score": 1, "id": "egdlo56"}, {"created_at": 1549909687.0, "distinguished": null, "type": "comment", "score": 1, "id": "eg8q11o"}, {"created_at": 1549909379.0, "distinguished": null, "type": "comment", "score": 1, "id": "eg8ph8n"}, {"created_at": 1549909164.0, "distinguished": null, "type": "comment", "score": 2, "id": "eg8p3fg"}, {"created_at": 1549823381.0, "distinguished": null, "type": "comment", "score": 6, "id": "eg63qdm"}, {"created_at": 1549792945.0, "distinguished": null, "type": "comment", "score": 1, "id": "eg5cb1t"}, {"created_at": 1549792764.0, "distinguished": null, "type": "comment", "score": 2, "id": "eg5c7kx"}, {"created_at": 1549792395.0, "distinguished": null, "type": "comment", "score": 1, "id": "eg5c0gx"}, {"created_at": 1549790356.0, "distinguished": null, "type": "comment", "score": 1, "id": "eg5avk7"}, {"created_at": 1549741868.0, "distinguished": null, "type": "comment", "score": 2, "id": "eg3wh1c"}, {"created_at": 1549718976.0, "distinguished": null, "type": "comment", "score": 2, "id": "eg35c8w"}, {"created_at": 1549718845.0, "distinguished": null, "type": "comment", "score": 2, "id": "eg3589d"}, {"created_at": 1549718301.0, "distinguished": null, "type": "comment", "score": 2, "id": "eg34s31"}, {"created_at": 1549703462.0, "distinguished": null, "type": "comment", "score": 2, "id": "eg2v9lt"}, {"created_at": 1549525928.0, "distinguished": null, "type": "comment", "score": 2, "id": "efxjfvi"}, {"created_at": 1549398706.0, "distinguished": null, "type": "comment", "score": 1, "id": "eftjc19"}, {"created_at": 1549398436.0, "distinguished": null, "type": "comment", "score": 1, "id": "eftixcp"}, {"created_at": 1549354876.0, "distinguished": null, "type": "comment", "score": 3, "id": "efs8qhk"}, {"created_at": 1549029583.0, "distinguished": null, "type": "comment", "score": 5, "id": "efipjfb"}, {"created_at": 1548960517.0, "distinguished": null, "type": "comment", "score": 2, "id": "efgn8ll"}, {"created_at": 1548959826.0, "distinguished": null, "type": "comment", "score": 3, "id": "efgm4u5"}, {"created_at": 1548951942.0, "distinguished": null, "type": "comment", "score": 1, "id": "efg9w2y"}, {"created_at": 1548893942.0, "distinguished": null, "type": "comment", "score": 0, "id": "efei2lh"}, {"created_at": 1548893423.0, "distinguished": null, "type": "comment", "score": 3, "id": "efeheil"}, {"created_at": 1548779113.0, "distinguished": null, "type": "comment", "score": 1, "id": "ef9t232"}, {"created_at": 1548706579.0, "distinguished": null, "type": "comment", "score": 2, "id": "ef7842r"}, {"created_at": 1548694028.0, "distinguished": null, "type": "comment", "score": 1, "id": "ef6navm"}, {"created_at": 1548692781.0, "distinguished": null, "type": "comment", "score": 1, "id": "ef6lc49"}, {"created_at": 1548691369.0, "distinguished": null, "type": "comment", "score": 0, "id": "ef6j39c"}, {"created_at": 1548591503.0, "distinguished": null, "type": "comment", "score": 5, "id": "ef3dz2e"}, {"created_at": 1548581005.0, "distinguished": null, "type": "comment", "score": 1, "id": "ef33nw2"}, {"created_at": 1548495601.0, "distinguished": null, "type": "comment", "score": 0, "id": "ef045ih"}, {"created_at": 1547545833.0, "distinguished": null, "type": "comment", "score": 1, "id": "ee3zp1v"}, {"created_at": 1547490275.0, "distinguished": null, "type": "comment", "score": 2, "id": "ee293p0"}, {"created_at": 1547283366.0, "distinguished": null, "type": "comment", "score": 1, "id": "edvobme"}, {"created_at": 1547282845.0, "distinguished": null, "type": "comment", "score": 1, "id": "edvnrfm"}, {"created_at": 1547282312.0, "distinguished": null, "type": "comment", "score": 1, "id": "edvn6iz"}, {"created_at": 1547282289.0, "distinguished": null, "type": "comment", "score": 1, "id": "edvn5kt"}, {"created_at": 1547282259.0, "distinguished": null, "type": "comment", "score": 2, "id": "edvn4by"}, {"created_at": 1547242174.0, "distinguished": null, "type": "submission", "score": 0, "id": "af06qn"}], "id": "MouseReview"}, {"post_data": [{"created_at": 1555176671.0, "distinguished": null, "type": "comment", "score": 1, "id": "ekt5ory"}, {"created_at": 1554910764.0, "distinguished": null, "type": "comment", "score": 7, "id": "ekjyd2i"}, {"created_at": 1554897893.0, "distinguished": null, "type": "comment", "score": 4, "id": "ekjhoi3"}, {"created_at": 1554531318.0, "distinguished": null, "type": "comment", "score": 2, "id": "ek8e7js"}, {"created_at": 1554521992.0, "distinguished": null, "type": "comment", "score": 2, "id": "ek86m9b"}, {"created_at": 1554135510.0, "distinguished": null, "type": "comment", "score": 2, "id": "ejvrogo"}, {"created_at": 1554026498.0, "distinguished": null, "type": "comment", "score": 2, "id": "ejsnjax"}, {"created_at": 1553797892.0, "distinguished": null, "type": "comment", "score": 9, "id": "ejleyc5"}], "id": "Wildlands"}, {"post_data": [{"created_at": 1554842876.0, "distinguished": null, "type": "comment", "score": 72, "id": "ekhyh7x"}], "id": "MilitaryPorn"}, {"post_data": [{"created_at": 1554620079.0, "distinguished": null, "type": "comment", "score": 3, "id": "ekatmhl"}, {"created_at": 1554486164.0, "distinguished": null, "type": "comment", "score": 3, "id": "ek6w4sf"}, {"created_at": 1554306210.0, "distinguished": null, "type": "comment", "score": 1, "id": "ek12v1j"}, {"created_at": 1554238839.0, "distinguished": null, "type": "comment", "score": 1, "id": "ejz5qt0"}, {"created_at": 1553902095.0, "distinguished": null, "type": "comment", "score": 3, "id": "ejp4rxp"}, {"created_at": 1550440440.0, "distinguished": null, "type": "comment", "score": 1, "id": "egor4x8"}, {"created_at": 1550439535.0, "distinguished": null, "type": "comment", "score": 1, "id": "egopzag"}, {"created_at": 1550438948.0, "distinguished": null, "type": "comment", "score": 1, "id": "egop8yy"}, {"created_at": 1550434905.0, "distinguished": null, "type": "comment", "score": 1, "id": "egok7y5"}, {"created_at": 1550434400.0, "distinguished": null, "type": "comment", "score": 3, "id": "egojl31"}, {"created_at": 1550255823.0, "distinguished": null, "type": "comment", "score": 4, "id": "egjokof"}, {"created_at": 1549958583.0, "distinguished": null, "type": "comment", "score": 1, "id": "egaky0h"}, {"created_at": 1548599082.0, "distinguished": null, "type": "comment", "score": 1, "id": "ef3m944"}], "id": "MechanicalKeyboards"}], "links": [{"time_delta": [106391.0], "count": 1, "source": "GhostRecon", "target": "pics"}, {"time_delta": [11098.0], "count": 1, "source": "GhostRecon", "target": "arma"}, {"time_delta": [3432.0, 19716.0, 94926.0, 3927.0, 3020.0, 4752.0, 1567.0, 17071.0, 990.0, 3065.0, 3898.0, 87175.0, 45.0, 22020.0, 212736.0, 28171.0, 32061.0, 77044.0, 81430.0], "count": 19, "source": "GhostRecon", "target": "GhostRecon"}, {"time_delta": [30361.0, 69420.0], "count": 2, "source": "GhostRecon", "target": "MouseReview"}, {"time_delta": [38902.0], "count": 1, "source": "GhostRecon", "target": "linuxquestions"}, {"time_delta": [25086.0, 84907.0, 2002.0, 169672.0], "count": 4, "source": "GhostRecon", "target": "Wildlands"}, {"time_delta": [78158.0, 4104.0], "count": 2, "source": "GhostRecon", "target": "MechanicalKeyboards"}, {"time_delta": [462.0], "count": 1, "source": "arma", "target": "GhostRecon"}, {"time_delta": [11896.0], "count": 1, "source": "arma", "target": "arma"}, {"time_delta": [33513.0], "count": 1, "source": "arma", "target": "MouseReview"}, {"time_delta": [309.0], "count": 1, "source": "linuxquestions", "target": "arma"}, {"time_delta": [375.0], "count": 1, "source": "linuxquestions", "target": "MouseReview"}, {"time_delta": [1709339.0], "count": 1, "source": "linuxquestions", "target": "GhostRecon"}, {"time_delta": [6529.0], "count": 1, "source": "linuxquestions", "target": "linuxquestions"}, {"time_delta": [57296.0, 632514.0], "count": 2, "source": "MouseReview", "target": "linuxquestions"}, {"time_delta": [129233.0], "count": 1, "source": "MouseReview", "target": "Wildlands"}, {"time_delta": [10923.0, 25956.0, 191.0, 5367.0], "count": 4, "source": "MouseReview", "target": "GhostRecon"}, {"time_delta": [14164.0], "count": 1, "source": "MouseReview", "target": "MilitaryPorn"}, {"time_delta": [34669.0, 31581.0, 29566.0, 16543.0, 178.0, 507.0, 6981.0, 149420.0, 7730.0, 89334.0, 22522.0, 62462.0, 4308.0, 11439.0, 62630.0, 43697.0, 37942.0, 308.0, 215.0, 85783.0, 30436.0, 181.0, 369.0, 2039.0, 48488.0, 22892.0, 131.0, 544.0, 14839.0, 177534.0, 127222.0, 270.0, 43560.0, 325293.0, 69066.0, 691.0, 7884.0, 58000.0, 519.0, 114310.0, 72534.0, 12551.0, 1247.0, 1412.0, 10498.0, 85404.0, 949768.0, 55558.0, 206909.0, 521.0, 533.0, 23.0, 30.0, 40085.0], "count": 54, "source": "MouseReview", "target": "MouseReview"}, {"time_delta": [111.0, 112793.0, 48896.0, 7579.0], "count": 4, "source": "MouseReview", "target": "MechanicalKeyboards"}, {"time_delta": [10132.0], "count": 1, "source": "Wildlands", "target": "MouseReview"}, {"time_delta": [27631.0, 4052.0, 2085.0], "count": 3, "source": "Wildlands", "target": "GhostRecon"}, {"time_delta": [12871.0, 9326.0], "count": 2, "source": "Wildlands", "target": "Wildlands"}, {"time_delta": [88761.0, 104203.0], "count": 2, "source": "Wildlands", "target": "MechanicalKeyboards"}, {"time_delta": [55017.0], "count": 1, "source": "MilitaryPorn", "target": "Wildlands"}, {"time_delta": [9878.0, 10551.0, 76116.0, 15105.0, 102808.0, 92287.0], "count": 6, "source": "MechanicalKeyboards", "target": "MouseReview"}, {"time_delta": [599.0, 122401.0], "count": 2, "source": "MechanicalKeyboards", "target": "GhostRecon"}, {"time_delta": [67371.0, 905.0, 587.0, 4043.0, 505.0], "count": 5, "source": "MechanicalKeyboards", "target": "MechanicalKeyboards"}]}}