{"user": "2f758a581226818dd46334e2a3575da5479f7884", "user_type": "random_user", "data": {"directed": true, "multigraph": false, "graph": {}, "nodes": [{"post_data": [{"created_at": 1554594883.0, "distinguished": null, "type": "comment", "score": 2, "id": "eka4dps"}], "id": "MildlyVandalised"}, {"post_data": [{"created_at": 1554586500.0, "distinguished": null, "type": "comment", "score": 2, "id": "ek9urxg"}, {"created_at": 1554586373.0, "distinguished": null, "type": "comment", "score": 2, "id": "ek9umns"}, {"created_at": 1554585211.0, "distinguished": null, "type": "comment", "score": 1, "id": "ek9tacx"}, {"created_at": 1554585035.0, "distinguished": null, "type": "comment", "score": 2, "id": "ek9t30o"}, {"created_at": 1554577543.0, "distinguished": null, "type": "comment", "score": 5, "id": "ek9kdpj"}, {"created_at": 1554577236.0, "distinguished": null, "type": "comment", "score": 6, "id": "ek9k00w"}, {"created_at": 1554576982.0, "distinguished": null, "type": "comment", "score": 1, "id": "ek9jo72"}, {"created_at": 1554416198.0, "distinguished": null, "type": "comment", "score": 1, "id": "ek4ve2h"}, {"created_at": 1554415563.0, "distinguished": null, "type": "comment", "score": 0, "id": "ek4ujqx"}, {"created_at": 1554415432.0, "distinguished": null, "type": "comment", "score": 1, "id": "ek4udc5"}, {"created_at": 1554414958.0, "distinguished": null, "type": "comment", "score": 1, "id": "ek4tq6n"}, {"created_at": 1554414796.0, "distinguished": null, "type": "comment", "score": 2, "id": "ek4tia6"}, {"created_at": 1554414402.0, "distinguished": null, "type": "comment", "score": 2, "id": "ek4sywo"}, {"created_at": 1552357543.0, "distinguished": null, "type": "comment", "score": 1, "id": "eibpr6t"}, {"created_at": 1552357365.0, "distinguished": null, "type": "comment", "score": 1, "id": "eibpjbg"}], "id": "HollowKnight"}, {"post_data": [{"created_at": 1554574847.0, "distinguished": null, "type": "comment", "score": 2, "id": "ek9gv9s"}, {"created_at": 1554574327.0, "distinguished": null, "type": "comment", "score": 0, "id": "ek9g6hc"}], "id": "technicallythetruth"}, {"post_data": [{"created_at": 1552376622.0, "distinguished": null, "type": "comment", "score": 1, "id": "eic6j3j"}, {"created_at": 1552358498.0, "distinguished": null, "type": "comment", "score": 1, "id": "eibqwvm"}, {"created_at": 1552170626.0, "distinguished": null, "type": "comment", "score": 3, "id": "ei63nw9"}, {"created_at": 1552170364.0, "distinguished": null, "type": "comment", "score": 3, "id": "ei63cbv"}, {"created_at": 1552170233.0, "distinguished": null, "type": "comment", "score": 5, "id": "ei636s9"}, {"created_at": 1552170172.0, "distinguished": null, "type": "comment", "score": 4, "id": "ei6341p"}], "id": "Flatearther"}, {"post_data": [{"created_at": 1552356881.0, "distinguished": null, "type": "comment", "score": 1, "id": "eiboxpu"}], "id": "FunnyandSad"}, {"post_data": [{"created_at": 1552172893.0, "distinguished": null, "type": "comment", "score": 1, "id": "ei66cpm"}], "id": "sex"}, {"post_data": [{"created_at": 1552170109.0, "distinguished": null, "type": "comment", "score": 1, "id": "ei631e2"}], "id": "FlatEarthTheory"}, {"post_data": [{"created_at": 1552169739.0, "distinguished": null, "type": "submission", "score": 1, "id": "az8tzh"}], "id": "giofilms"}, {"post_data": [{"created_at": 1552153138.0, "distinguished": null, "type": "comment", "score": 2, "id": "ei5gwka"}], "id": "dank_meme"}, {"post_data": [{"created_at": 1551557511.0, "distinguished": null, "type": "comment", "score": 2, "id": "ehnerrv"}, {"created_at": 1551557329.0, "distinguished": null, "type": "comment", "score": 3, "id": "ehnej6i"}], "id": "nintendo"}, {"post_data": [{"created_at": 1550103218.0, "distinguished": null, "type": "comment", "score": 3, "id": "egf7kva"}, {"created_at": 1550007281.0, "distinguished": null, "type": "comment", "score": 3, "id": "egc3jsj"}, {"created_at": 1550007187.0, "distinguished": null, "type": "comment", "score": 1, "id": "egc3ekz"}, {"created_at": 1549911595.0, "distinguished": null, "type": "comment", "score": 1, "id": "eg8tgik"}, {"created_at": 1549911481.0, "distinguished": null, "type": "comment", "score": 1, "id": "eg8t90r"}, {"created_at": 1549911381.0, "distinguished": null, "type": "comment", "score": 1, "id": "eg8t2ie"}, {"created_at": 1549910997.0, "distinguished": null, "type": "comment", "score": 1, "id": "eg8sdov"}, {"created_at": 1549910903.0, "distinguished": null, "type": "comment", "score": 1, "id": "eg8s7nv"}, {"created_at": 1549910801.0, "distinguished": null, "type": "comment", "score": 1, "id": "eg8s103"}], "id": "EtikaRedditNetwork"}, {"post_data": [{"created_at": 1549821729.0, "distinguished": null, "type": "comment", "score": 0, "id": "eg61m4u"}, {"created_at": 1547229300.0, "distinguished": null, "type": "comment", "score": 1, "id": "edton4q"}, {"created_at": 1544480285.0, "distinguished": null, "type": "comment", "score": 1, "id": "ebivv7s"}], "id": "smashbros"}, {"post_data": [{"created_at": 1549172655.0, "distinguished": null, "type": "comment", "score": 1, "id": "efn4bna"}, {"created_at": 1549153565.0, "distinguished": null, "type": "comment", "score": 2, "id": "efmjif7"}], "id": "trashy"}, {"post_data": [{"created_at": 1549153251.0, "distinguished": null, "type": "comment", "score": 2, "id": "efmj5ig"}], "id": "Cringetopia"}, {"post_data": [{"created_at": 1548880027.0, "distinguished": null, "type": "comment", "score": 1, "id": "efdxs36"}], "id": "AccidentalRacism"}, {"post_data": [{"created_at": 1547833634.0, "distinguished": null, "type": "comment", "score": 1, "id": "eedd8qn"}, {"created_at": 1547762360.0, "distinguished": null, "type": "comment", "score": 1, "id": "eeb0mrv"}, {"created_at": 1547762340.0, "distinguished": null, "type": "comment", "score": 3, "id": "eeb0lov"}], "id": "comedyheaven"}, {"post_data": [{"created_at": 1547667973.0, "distinguished": null, "type": "comment", "score": 1, "id": "ee7st0k"}, {"created_at": 1546087575.0, "distinguished": null, "type": "comment", "score": 1, "id": "ecst0el"}], "id": "woooosh"}, {"post_data": [{"created_at": 1547272039.0, "distinguished": null, "type": "comment", "score": 1, "id": "edvdun7"}, {"created_at": 1545707250.0, "distinguished": null, "type": "comment", "score": 2, "id": "echyiji"}], "id": "foundthemobileuser"}, {"post_data": [{"created_at": 1547148943.0, "distinguished": null, "type": "comment", "score": 2, "id": "edqjkf5"}], "id": "ComedyCemetery"}, {"post_data": [{"created_at": 1546653938.0, "distinguished": null, "type": "comment", "score": 2, "id": "ed9r1xf"}, {"created_at": 1546549693.0, "distinguished": null, "type": "comment", "score": 2, "id": "ed6d7hl"}, {"created_at": 1545673458.0, "distinguished": null, "type": "comment", "score": 0, "id": "ecguhc6"}, {"created_at": 1545416991.0, "distinguished": null, "type": "comment", "score": 5, "id": "ec9mj84"}, {"created_at": 1543976741.0, "distinguished": null, "type": "comment", "score": 1, "id": "eb41g0f"}, {"created_at": 1543364026.0, "distinguished": null, "type": "comment", "score": 3, "id": "ealvut6"}, {"created_at": 1543363514.0, "distinguished": null, "type": "submission", "score": 17, "id": "a10nbj"}], "id": "gatekeeping"}, {"post_data": [{"created_at": 1546230499.0, "distinguished": null, "type": "comment", "score": 1, "id": "ecx9g5n"}, {"created_at": 1546088764.0, "distinguished": null, "type": "comment", "score": 3, "id": "ecstsic"}], "id": "funny"}, {"post_data": [{"created_at": 1545451535.0, "distinguished": null, "type": "comment", "score": 1, "id": "ecaqa9o"}], "id": "interestingasfuck"}, {"post_data": [{"created_at": 1544133707.0, "distinguished": null, "type": "comment", "score": 1, "id": "eb8ture"}], "id": "sbubby"}], "links": [{"time_delta": [8383.0], "count": 1, "source": "HollowKnight", "target": "MildlyVandalised"}, {"time_delta": [127.0, 1162.0, 176.0, 7492.0, 307.0, 254.0, 635.0, 131.0, 474.0, 162.0, 394.0, 178.0], "count": 12, "source": "HollowKnight", "target": "HollowKnight"}, {"time_delta": [158129.0], "count": 1, "source": "HollowKnight", "target": "technicallythetruth"}, {"time_delta": [955.0], "count": 1, "source": "HollowKnight", "target": "Flatearther"}, {"time_delta": [2135.0], "count": 1, "source": "technicallythetruth", "target": "HollowKnight"}, {"time_delta": [520.0], "count": 1, "source": "technicallythetruth", "target": "technicallythetruth"}, {"time_delta": [2037780.0], "count": 1, "source": "Flatearther", "target": "HollowKnight"}, {"time_delta": [18124.0, 262.0, 131.0, 61.0], "count": 4, "source": "Flatearther", "target": "Flatearther"}, {"time_delta": [2267.0], "count": 1, "source": "Flatearther", "target": "sex"}, {"time_delta": [484.0], "count": 1, "source": "FunnyandSad", "target": "HollowKnight"}, {"time_delta": [183988.0], "count": 1, "source": "sex", "target": "FunnyandSad"}, {"time_delta": [63.0], "count": 1, "source": "FlatEarthTheory", "target": "Flatearther"}, {"time_delta": [370.0], "count": 1, "source": "giofilms", "target": "FlatEarthTheory"}, {"time_delta": [16601.0], "count": 1, "source": "dank_meme", "target": "giofilms"}, {"time_delta": [595627.0], "count": 1, "source": "nintendo", "target": "dank_meme"}, {"time_delta": [182.0], "count": 1, "source": "nintendo", "target": "nintendo"}, {"time_delta": [1454111.0], "count": 1, "source": "EtikaRedditNetwork", "target": "nintendo"}, {"time_delta": [95937.0, 94.0, 95592.0, 114.0, 100.0, 384.0, 94.0, 102.0], "count": 8, "source": "EtikaRedditNetwork", "target": "EtikaRedditNetwork"}, {"time_delta": [89072.0], "count": 1, "source": "smashbros", "target": "EtikaRedditNetwork"}, {"time_delta": [42739.0], "count": 1, "source": "smashbros", "target": "foundthemobileuser"}, {"time_delta": [936706.0], "count": 1, "source": "smashbros", "target": "gatekeeping"}, {"time_delta": [649074.0], "count": 1, "source": "trashy", "target": "smashbros"}, {"time_delta": [19090.0], "count": 1, "source": "trashy", "target": "trashy"}, {"time_delta": [314.0], "count": 1, "source": "Cringetopia", "target": "trashy"}, {"time_delta": [273224.0], "count": 1, "source": "AccidentalRacism", "target": "Cringetopia"}, {"time_delta": [1046393.0], "count": 1, "source": "comedyheaven", "target": "AccidentalRacism"}, {"time_delta": [71274.0, 20.0], "count": 2, "source": "comedyheaven", "target": "comedyheaven"}, {"time_delta": [94367.0], "count": 1, "source": "woooosh", "target": "comedyheaven"}, {"time_delta": [1189.0], "count": 1, "source": "woooosh", "target": "funny"}, {"time_delta": [395934.0, 380325.0], "count": 2, "source": "foundthemobileuser", "target": "woooosh"}, {"time_delta": [80357.0], "count": 1, "source": "ComedyCemetery", "target": "smashbros"}, {"time_delta": [495005.0], "count": 1, "source": "gatekeeping", "target": "ComedyCemetery"}, {"time_delta": [104245.0, 612715.0, 512.0], "count": 3, "source": "gatekeeping", "target": "gatekeeping"}, {"time_delta": [33792.0], "count": 1, "source": "gatekeeping", "target": "foundthemobileuser"}, {"time_delta": [34544.0], "count": 1, "source": "gatekeeping", "target": "interestingasfuck"}, {"time_delta": [156966.0], "count": 1, "source": "gatekeeping", "target": "sbubby"}, {"time_delta": [319194.0], "count": 1, "source": "funny", "target": "gatekeeping"}, {"time_delta": [141735.0], "count": 1, "source": "funny", "target": "funny"}, {"time_delta": [221923.0], "count": 1, "source": "interestingasfuck", "target": "gatekeeping"}, {"time_delta": [346578.0], "count": 1, "source": "sbubby", "target": "smashbros"}]}}