{"user": "54f48a84552aa4fb09c05f0586c5c95023ef422e", "user_type": "random_user", "data": {"directed": true, "multigraph": false, "graph": {}, "nodes": [{"post_data": [{"created_at": 1555346875.0, "distinguished": null, "type": "comment", "score": 9, "id": "ekya2fg"}, {"created_at": 1555338509.0, "distinguished": null, "type": "comment", "score": 1, "id": "ekxxgb1"}, {"created_at": 1553199871.0, "distinguished": null, "type": "comment", "score": 2, "id": "ej2fxka"}, {"created_at": 1553187984.0, "distinguished": null, "type": "submission", "score": 1, "id": "b3t2k9"}], "id": "confession"}, {"post_data": [{"created_at": 1555346382.0, "distinguished": null, "type": "comment", "score": 1, "id": "eky997v"}, {"created_at": 1555346170.0, "distinguished": null, "type": "comment", "score": 1, "id": "eky8wya"}, {"created_at": 1555345592.0, "distinguished": null, "type": "comment", "score": 1, "id": "eky80gl"}, {"created_at": 1555344115.0, "distinguished": null, "type": "submission", "score": 155, "id": "bdhphx"}], "id": "unpopularopinion"}, {"post_data": [{"created_at": 1555343658.0, "distinguished": null, "type": "comment", "score": 1, "id": "eky4ype"}, {"created_at": 1555104947.0, "distinguished": null, "type": "submission", "score": 1, "id": "bcj5r5"}, {"created_at": 1555018315.0, "distinguished": null, "type": "submission", "score": 2, "id": "bc5gta"}, {"created_at": 1555010065.0, "distinguished": null, "type": "comment", "score": 1, "id": "eknk1y3"}, {"created_at": 1554995789.0, "distinguished": null, "type": "comment", "score": 3, "id": "ekmx9jn"}, {"created_at": 1554835198.0, "distinguished": null, "type": "comment", "score": 3, "id": "ekhmvw7"}, {"created_at": 1554834748.0, "distinguished": null, "type": "comment", "score": 2, "id": "ekhm7j1"}, {"created_at": 1554822433.0, "distinguished": null, "type": "submission", "score": 0, "id": "bb9191"}, {"created_at": 1554819957.0, "distinguished": null, "type": "comment", "score": 1, "id": "ekgy4le"}, {"created_at": 1554754869.0, "distinguished": null, "type": "comment", "score": 15, "id": "ekeyhbh"}, {"created_at": 1554753676.0, "distinguished": null, "type": "comment", "score": 1, "id": "ekewdxi"}, {"created_at": 1554752874.0, "distinguished": null, "type": "comment", "score": 1, "id": "ekev0ac"}, {"created_at": 1554749180.0, "distinguished": null, "type": "comment", "score": 1, "id": "ekeomjh"}, {"created_at": 1554748907.0, "distinguished": null, "type": "comment", "score": 2, "id": "ekeo62u"}, {"created_at": 1554748859.0, "distinguished": null, "type": "comment", "score": 1, "id": "ekeo36h"}, {"created_at": 1554748770.0, "distinguished": null, "type": "comment", "score": 2, "id": "ekenxsd"}, {"created_at": 1554748630.0, "distinguished": null, "type": "comment", "score": 2, "id": "ekenphk"}, {"created_at": 1554748552.0, "distinguished": null, "type": "comment", "score": 1, "id": "ekenkwj"}, {"created_at": 1554747932.0, "distinguished": null, "type": "comment", "score": 2, "id": "ekemj7u"}, {"created_at": 1554741347.0, "distinguished": null, "type": "comment", "score": 393, "id": "ekec00b"}, {"created_at": 1554741148.0, "distinguished": null, "type": "comment", "score": 1, "id": "ekeboz7"}, {"created_at": 1554741068.0, "distinguished": null, "type": "comment", "score": 1, "id": "ekebkf4"}], "id": "AskReddit"}, {"post_data": [{"created_at": 1555343388.0, "distinguished": null, "type": "comment", "score": 98, "id": "eky4jwi"}], "id": "DoesAnybodyElse"}, {"post_data": [{"created_at": 1555341616.0, "distinguished": null, "type": "submission", "score": 1, "id": "bdh76o"}], "id": "changemyview"}, {"post_data": [{"created_at": 1555103941.0, "distinguished": null, "type": "comment", "score": 7, "id": "ekr1dbr"}, {"created_at": 1554989593.0, "distinguished": null, "type": "comment", "score": 1, "id": "ekmnwt5"}], "id": "thebachelor"}, {"post_data": [{"created_at": 1555100721.0, "distinguished": null, "type": "comment", "score": 109, "id": "ekqw0sp"}, {"created_at": 1554992553.0, "distinguished": null, "type": "comment", "score": 2, "id": "ekmsd6f"}, {"created_at": 1554843751.0, "distinguished": null, "type": "comment", "score": 0, "id": "ekhztc8"}, {"created_at": 1554843620.0, "distinguished": null, "type": "comment", "score": 2, "id": "ekhzm74"}, {"created_at": 1554760080.0, "distinguished": null, "type": "comment", "score": 1, "id": "ekf7fe7"}, {"created_at": 1554759828.0, "distinguished": null, "type": "comment", "score": 1, "id": "ekf71h4"}, {"created_at": 1554759025.0, "distinguished": null, "type": "comment", "score": 1, "id": "ekf5qa1"}, {"created_at": 1554758157.0, "distinguished": null, "type": "comment", "score": 1, "id": "ekf494r"}], "id": "AskWomen"}, {"post_data": [{"created_at": 1555086264.0, "distinguished": null, "type": "comment", "score": 2, "id": "ekq6ktg"}], "id": "offmychest"}, {"post_data": [{"created_at": 1555076418.0, "distinguished": null, "type": "comment", "score": 2, "id": "ekpqhsa"}, {"created_at": 1555076339.0, "distinguished": null, "type": "comment", "score": 16, "id": "ekpqdep"}, {"created_at": 1554846611.0, "distinguished": null, "type": "comment", "score": 3, "id": "eki3wrf"}, {"created_at": 1554846029.0, "distinguished": null, "type": "comment", "score": 4, "id": "eki33dy"}, {"created_at": 1554843482.0, "distinguished": null, "type": "comment", "score": 94, "id": "ekhzeha"}, {"created_at": 1553289811.0, "distinguished": null, "type": "comment", "score": 4, "id": "ej5ewqu"}, {"created_at": 1553289386.0, "distinguished": null, "type": "comment", "score": 2, "id": "ej5ea3a"}, {"created_at": 1553289310.0, "distinguished": null, "type": "comment", "score": 2, "id": "ej5e604"}, {"created_at": 1553289246.0, "distinguished": null, "type": "comment", "score": 4, "id": "ej5e2il"}, {"created_at": 1553289199.0, "distinguished": null, "type": "comment", "score": 1, "id": "ej5e02q"}, {"created_at": 1553289095.0, "distinguished": null, "type": "comment", "score": 8, "id": "ej5duhs"}, {"created_at": 1553289035.0, "distinguished": null, "type": "comment", "score": 10, "id": "ej5dr4b"}], "id": "ImpracticalJokers"}, {"post_data": [{"created_at": 1554995400.0, "distinguished": null, "type": "submission", "score": 5, "id": "bc1023"}, {"created_at": 1553547083.0, "distinguished": null, "type": "comment", "score": 1, "id": "ejd85i4"}, {"created_at": 1553547071.0, "distinguished": null, "type": "comment", "score": 1, "id": "ejd84u6"}, {"created_at": 1553525307.0, "distinguished": null, "type": "submission", "score": 2, "id": "b5bl1h"}], "id": "Career"}, {"post_data": [{"created_at": 1554993750.0, "distinguished": null, "type": "comment", "score": 3, "id": "ekmu5rk"}, {"created_at": 1554993652.0, "distinguished": null, "type": "comment", "score": 3, "id": "ekmu0ga"}, {"created_at": 1554993408.0, "distinguished": null, "type": "submission", "score": 67, "id": "bc0mf9"}], "id": "TheActHulu"}, {"post_data": [{"created_at": 1554845283.0, "distinguished": null, "type": "comment", "score": 2, "id": "eki21ab"}, {"created_at": 1554845278.0, "distinguished": null, "type": "comment", "score": 2, "id": "eki211d"}, {"created_at": 1554844254.0, "distinguished": null, "type": "submission", "score": 2, "id": "bbdfti"}, {"created_at": 1554824476.0, "distinguished": null, "type": "comment", "score": 1, "id": "ekh5cvd"}, {"created_at": 1554824106.0, "distinguished": null, "type": "comment", "score": 2, "id": "ekh4rk8"}, {"created_at": 1554823785.0, "distinguished": null, "type": "submission", "score": 1, "id": "bb9ank"}], "id": "tipofmytongue"}, {"post_data": [{"created_at": 1554829324.0, "distinguished": null, "type": "comment", "score": 0, "id": "ekhd8uc"}, {"created_at": 1554829311.0, "distinguished": null, "type": "comment", "score": -2, "id": "ekhd7zj"}, {"created_at": 1554820754.0, "distinguished": null, "type": "comment", "score": -2, "id": "ekgzdf8"}], "id": "WhitePeopleTwitter"}, {"post_data": [{"created_at": 1554756988.0, "distinguished": null, "type": "submission", "score": 0, "id": "baz1jt"}, {"created_at": 1554756568.0, "distinguished": null, "type": "comment", "score": -1, "id": "ekf1gdm"}], "id": "AskMen"}, {"post_data": [{"created_at": 1554749244.0, "distinguished": null, "type": "submission", "score": 54, "id": "baxihm"}], "id": "antiMLM"}, {"post_data": [{"created_at": 1554738717.0, "distinguished": null, "type": "submission", "score": 2, "id": "bavfvq"}], "id": "relationship_advice"}, {"post_data": [{"created_at": 1553867952.0, "distinguished": null, "type": "submission", "score": 1, "id": "b6xlvm"}], "id": "hygiene"}, {"post_data": [{"created_at": 1553551075.0, "distinguished": null, "type": "submission", "score": 12, "id": "b5h2c5"}], "id": "lasik"}, {"post_data": [{"created_at": 1553549639.0, "distinguished": null, "type": "comment", "score": 1, "id": "ejdc6uh"}, {"created_at": 1553549498.0, "distinguished": null, "type": "comment", "score": 1, "id": "ejdbz01"}, {"created_at": 1553547009.0, "distinguished": null, "type": "comment", "score": 2, "id": "ejd81ae"}, {"created_at": 1553183082.0, "distinguished": null, "type": "submission", "score": 3, "id": "b3s2f7"}], "id": "sex"}], "links": [{"time_delta": [3107.0], "count": 1, "source": "confession", "target": "changemyview"}, {"time_delta": [89164.0], "count": 1, "source": "confession", "target": "ImpracticalJokers"}, {"time_delta": [11887.0], "count": 1, "source": "confession", "target": "confession"}, {"time_delta": [493.0], "count": 1, "source": "unpopularopinion", "target": "confession"}, {"time_delta": [212.0, 578.0, 1477.0], "count": 3, "source": "unpopularopinion", "target": "unpopularopinion"}, {"time_delta": [457.0], "count": 1, "source": "AskReddit", "target": "unpopularopinion"}, {"time_delta": [233562.0], "count": 1, "source": "AskReddit", "target": "confession"}, {"time_delta": [58024.0, 8284.0], "count": 2, "source": "AskReddit", "target": "ImpracticalJokers"}, {"time_delta": [8250.0, 14276.0, 450.0, 1193.0, 802.0, 273.0, 48.0, 89.0, 140.0, 78.0, 620.0, 6585.0, 199.0, 80.0], "count": 14, "source": "AskReddit", "target": "AskReddit"}, {"time_delta": [1352.0], "count": 1, "source": "AskReddit", "target": "tipofmytongue"}, {"time_delta": [797.0], "count": 1, "source": "AskReddit", "target": "WhitePeopleTwitter"}, {"time_delta": [1699.0], "count": 1, "source": "AskReddit", "target": "AskMen"}, {"time_delta": [64.0], "count": 1, "source": "AskReddit", "target": "antiMLM"}, {"time_delta": [270.0], "count": 1, "source": "DoesAnybodyElse", "target": "AskReddit"}, {"time_delta": [1772.0], "count": 1, "source": "changemyview", "target": "DoesAnybodyElse"}, {"time_delta": [1006.0], "count": 1, "source": "thebachelor", "target": "AskReddit"}, {"time_delta": [2960.0], "count": 1, "source": "thebachelor", "target": "AskWomen"}, {"time_delta": [3220.0], "count": 1, "source": "AskWomen", "target": "thebachelor"}, {"time_delta": [855.0], "count": 1, "source": "AskWomen", "target": "TheActHulu"}, {"time_delta": [503.0], "count": 1, "source": "AskWomen", "target": "tipofmytongue"}, {"time_delta": [131.0, 252.0, 803.0, 868.0], "count": 4, "source": "AskWomen", "target": "AskWomen"}, {"time_delta": [59877.0], "count": 1, "source": "AskWomen", "target": "AskReddit"}, {"time_delta": [14457.0], "count": 1, "source": "offmychest", "target": "AskWomen"}, {"time_delta": [9846.0], "count": 1, "source": "ImpracticalJokers", "target": "offmychest"}, {"time_delta": [79.0, 582.0, 425.0, 76.0, 64.0, 47.0, 104.0, 60.0], "count": 8, "source": "ImpracticalJokers", "target": "ImpracticalJokers"}, {"time_delta": [142982.0], "count": 1, "source": "ImpracticalJokers", "target": "thebachelor"}, {"time_delta": [138.0], "count": 1, "source": "ImpracticalJokers", "target": "AskWomen"}, {"time_delta": [235496.0], "count": 1, "source": "ImpracticalJokers", "target": "Career"}, {"time_delta": [389.0], "count": 1, "source": "Career", "target": "AskReddit"}, {"time_delta": [2415.0, 21702.0], "count": 2, "source": "Career", "target": "sex"}, {"time_delta": [12.0], "count": 1, "source": "Career", "target": "Career"}, {"time_delta": [1650.0], "count": 1, "source": "TheActHulu", "target": "Career"}, {"time_delta": [98.0, 244.0], "count": 2, "source": "TheActHulu", "target": "TheActHulu"}, {"time_delta": [746.0], "count": 1, "source": "tipofmytongue", "target": "ImpracticalJokers"}, {"time_delta": [5.0, 1024.0, 370.0, 321.0], "count": 4, "source": "tipofmytongue", "target": "tipofmytongue"}, {"time_delta": [4835.0], "count": 1, "source": "tipofmytongue", "target": "WhitePeopleTwitter"}, {"time_delta": [5424.0, 1679.0], "count": 2, "source": "WhitePeopleTwitter", "target": "AskReddit"}, {"time_delta": [13.0], "count": 1, "source": "WhitePeopleTwitter", "target": "WhitePeopleTwitter"}, {"time_delta": [1169.0], "count": 1, "source": "AskMen", "target": "AskWomen"}, {"time_delta": [420.0], "count": 1, "source": "AskMen", "target": "AskMen"}, {"time_delta": [3630.0], "count": 1, "source": "antiMLM", "target": "AskReddit"}, {"time_delta": [2351.0], "count": 1, "source": "relationship_advice", "target": "AskReddit"}, {"time_delta": [870765.0], "count": 1, "source": "hygiene", "target": "relationship_advice"}, {"time_delta": [316877.0], "count": 1, "source": "lasik", "target": "hygiene"}, {"time_delta": [1436.0], "count": 1, "source": "sex", "target": "lasik"}, {"time_delta": [141.0], "count": 1, "source": "sex", "target": "sex"}, {"time_delta": [62.0], "count": 1, "source": "sex", "target": "Career"}, {"time_delta": [4902.0], "count": 1, "source": "sex", "target": "confession"}]}}