{"user": "8f6456b919a69e0cf379f347686353456aaba9d3", "user_type": "random_user", "data": {"directed": true, "multigraph": false, "graph": {}, "nodes": [{"post_data": [{"created_at": 1555488492.0, "distinguished": null, "type": "comment", "score": 1, "id": "el358t5"}, {"created_at": 1555481219.0, "distinguished": null, "type": "comment", "score": 1, "id": "el30ceg"}], "id": "confessions"}, {"post_data": [{"created_at": 1555230991.0, "distinguished": null, "type": "comment", "score": 39, "id": "ekuylnn"}, {"created_at": 1554871992.0, "distinguished": null, "type": "comment", "score": 0, "id": "ekizol7"}], "id": "WTF"}, {"post_data": [{"created_at": 1555198572.0, "distinguished": null, "type": "comment", "score": 6, "id": "eku1y2q"}], "id": "rant"}, {"post_data": [{"created_at": 1555080857.0, "distinguished": null, "type": "comment", "score": 2, "id": "ekpxqc6"}, {"created_at": 1555050747.0, "distinguished": null, "type": "comment", "score": 2, "id": "ekp03y9"}], "id": "precognition"}, {"post_data": [{"created_at": 1555054147.0, "distinguished": null, "type": "comment", "score": 1, "id": "ekp3873"}, {"created_at": 1555053369.0, "distinguished": null, "type": "comment", "score": 3, "id": "ekp2iqv"}, {"created_at": 1554287187.0, "distinguished": null, "type": "comment", "score": 2, "id": "ek0h5rq"}, {"created_at": 1554285546.0, "distinguished": null, "type": "comment", "score": 2, "id": "ek0g6sz"}], "id": "tifu"}, {"post_data": [{"created_at": 1554997932.0, "distinguished": null, "type": "comment", "score": 1, "id": "ekn0mri"}, {"created_at": 1554987898.0, "distinguished": null, "type": "comment", "score": 1, "id": "ekmlivh"}], "id": "relationship_advice"}, {"post_data": [{"created_at": 1554973125.0, "distinguished": null, "type": "comment", "score": 3, "id": "ekm65ye"}, {"created_at": 1554970898.0, "distinguished": null, "type": "comment", "score": 1, "id": "ekm4lsm"}, {"created_at": 1554251617.0, "distinguished": null, "type": "comment", "score": 5, "id": "ejzmibd"}, {"created_at": 1553757922.0, "distinguished": null, "type": "comment", "score": 1, "id": "ejk3h1e"}, {"created_at": 1553753539.0, "distinguished": null, "type": "comment", "score": 2, "id": "ejk0avs"}], "id": "MandelaEffect"}, {"post_data": [{"created_at": 1554934820.0, "distinguished": null, "type": "comment", "score": 4, "id": "ekl1886"}, {"created_at": 1553804295.0, "distinguished": null, "type": "comment", "score": 4, "id": "ejlqc4a"}, {"created_at": 1553793150.0, "distinguished": null, "type": "comment", "score": 1, "id": "ejl6z5i"}, {"created_at": 1553782420.0, "distinguished": null, "type": "comment", "score": 2, "id": "ejkph89"}, {"created_at": 1553760416.0, "distinguished": null, "type": "comment", "score": 2, "id": "ejk50o9"}, {"created_at": 1553759386.0, "distinguished": null, "type": "comment", "score": 3, "id": "ejk4ejn"}, {"created_at": 1553756322.0, "distinguished": null, "type": "submission", "score": 16, "id": "b6fkzl"}, {"created_at": 1552651692.0, "distinguished": null, "type": "comment", "score": 2, "id": "eikyo63"}, {"created_at": 1552224120.0, "distinguished": null, "type": "comment", "score": 1, "id": "ei7e14f"}], "id": "Glitch_in_the_Matrix"}, {"post_data": [{"created_at": 1554804387.0, "distinguished": null, "type": "comment", "score": 2, "id": "ekgijw2"}, {"created_at": 1554802855.0, "distinguished": null, "type": "comment", "score": 1, "id": "ekghnpf"}, {"created_at": 1554799556.0, "distinguished": null, "type": "comment", "score": 1, "id": "ekgfvhl"}, {"created_at": 1554038991.0, "distinguished": null, "type": "comment", "score": 2, "id": "ejswab6"}, {"created_at": 1553793183.0, "distinguished": null, "type": "comment", "score": 2, "id": "ejl719i"}, {"created_at": 1553764929.0, "distinguished": null, "type": "comment", "score": 1, "id": "ejk7pdd"}, {"created_at": 1553763376.0, "distinguished": null, "type": "comment", "score": 1, "id": "ejk6rq4"}, {"created_at": 1553763016.0, "distinguished": null, "type": "comment", "score": 7, "id": "ejk6ka4"}], "id": "sad"}, {"post_data": [{"created_at": 1554796902.0, "distinguished": null, "type": "comment", "score": 32, "id": "ekgefhl"}, {"created_at": 1554213557.0, "distinguished": null, "type": "comment", "score": 1, "id": "ejy44kr"}, {"created_at": 1553758730.0, "distinguished": null, "type": "comment", "score": 1, "id": "ejk3zq8"}, {"created_at": 1552035524.0, "distinguished": null, "type": "comment", "score": 1, "id": "ei24mdl"}], "id": "nosleep"}, {"post_data": [{"created_at": 1554283682.0, "distinguished": null, "type": "comment", "score": 5, "id": "ek0f5kt"}], "id": "Thetruthishere"}, {"post_data": [{"created_at": 1553848373.0, "distinguished": null, "type": "comment", "score": 1, "id": "ejn6y39"}, {"created_at": 1553805082.0, "distinguished": null, "type": "comment", "score": 2, "id": "ejlrqmc"}], "id": "ExNoContact"}, {"post_data": [{"created_at": 1553710399.0, "distinguished": null, "type": "comment", "score": 5, "id": "ejif4af"}], "id": "Unexpected"}, {"post_data": [{"created_at": 1552602879.0, "distinguished": null, "type": "comment", "score": 1, "id": "eijolvn"}], "id": "AskReddit"}], "links": [{"time_delta": [7273.0], "count": 1, "source": "confessions", "target": "confessions"}, {"time_delta": [250228.0], "count": 1, "source": "WTF", "target": "confessions"}, {"time_delta": [62828.0], "count": 1, "source": "WTF", "target": "Glitch_in_the_Matrix"}, {"time_delta": [32419.0], "count": 1, "source": "rant", "target": "WTF"}, {"time_delta": [117715.0], "count": 1, "source": "precognition", "target": "rant"}, {"time_delta": [2622.0], "count": 1, "source": "precognition", "target": "tifu"}, {"time_delta": [26710.0], "count": 1, "source": "tifu", "target": "precognition"}, {"time_delta": [778.0, 1641.0], "count": 2, "source": "tifu", "target": "tifu"}, {"time_delta": [509715.0], "count": 1, "source": "tifu", "target": "nosleep"}, {"time_delta": [52815.0], "count": 1, "source": "relationship_advice", "target": "precognition"}, {"time_delta": [10034.0], "count": 1, "source": "relationship_advice", "target": "relationship_advice"}, {"time_delta": [14773.0], "count": 1, "source": "MandelaEffect", "target": "relationship_advice"}, {"time_delta": [2227.0], "count": 1, "source": "MandelaEffect", "target": "MandelaEffect"}, {"time_delta": [32065.0], "count": 1, "source": "MandelaEffect", "target": "Thetruthishere"}, {"time_delta": [808.0], "count": 1, "source": "MandelaEffect", "target": "nosleep"}, {"time_delta": [2783.0], "count": 1, "source": "MandelaEffect", "target": "Glitch_in_the_Matrix"}, {"time_delta": [36078.0, 1600.0], "count": 2, "source": "Glitch_in_the_Matrix", "target": "MandelaEffect"}, {"time_delta": [787.0], "count": 1, "source": "Glitch_in_the_Matrix", "target": "ExNoContact"}, {"time_delta": [33.0, 2600.0], "count": 2, "source": "Glitch_in_the_Matrix", "target": "sad"}, {"time_delta": [10730.0, 1030.0], "count": 2, "source": "Glitch_in_the_Matrix", "target": "Glitch_in_the_Matrix"}, {"time_delta": [1058707.0], "count": 1, "source": "Glitch_in_the_Matrix", "target": "Unexpected"}, {"time_delta": [378759.0], "count": 1, "source": "Glitch_in_the_Matrix", "target": "AskReddit"}, {"time_delta": [67605.0], "count": 1, "source": "sad", "target": "WTF"}, {"time_delta": [1532.0, 3299.0, 1553.0, 360.0], "count": 4, "source": "sad", "target": "sad"}, {"time_delta": [174566.0], "count": 1, "source": "sad", "target": "nosleep"}, {"time_delta": [11112.0, 17491.0], "count": 2, "source": "sad", "target": "Glitch_in_the_Matrix"}, {"time_delta": [2654.0], "count": 1, "source": "nosleep", "target": "sad"}, {"time_delta": [38060.0], "count": 1, "source": "nosleep", "target": "MandelaEffect"}, {"time_delta": [656.0, 188596.0], "count": 2, "source": "nosleep", "target": "Glitch_in_the_Matrix"}, {"time_delta": [1864.0], "count": 1, "source": "Thetruthishere", "target": "tifu"}, {"time_delta": [190618.0], "count": 1, "source": "ExNoContact", "target": "sad"}, {"time_delta": [43291.0], "count": 1, "source": "ExNoContact", "target": "ExNoContact"}, {"time_delta": [43140.0], "count": 1, "source": "Unexpected", "target": "MandelaEffect"}, {"time_delta": [48813.0], "count": 1, "source": "AskReddit", "target": "Glitch_in_the_Matrix"}]}}