{"user": "96dbe7ae19aa2acdb79d4213eea19227174bba45", "user_type": "random_user", "data": {"directed": true, "multigraph": false, "graph": {}, "nodes": [{"post_data": [{"created_at": 1555060466.0, "distinguished": null, "type": "comment", "score": 19, "id": "ekp8cj7"}, {"created_at": 1524671693.0, "distinguished": null, "type": "comment", "score": 1, "id": "dxy5dy4"}, {"created_at": 1521902988.0, "distinguished": null, "type": "comment", "score": 0, "id": "dw7occ3"}, {"created_at": 1521860271.0, "distinguished": null, "type": "comment", "score": 34, "id": "dw728y9"}, {"created_at": 1518489488.0, "distinguished": null, "type": "comment", "score": 2, "id": "du5t4yp"}, {"created_at": 1509025218.0, "distinguished": null, "type": "submission", "score": 10, "id": "78vm14"}, {"created_at": 1502409294.0, "distinguished": null, "type": "comment", "score": 1, "id": "dlg9hqs"}], "id": "northernlion"}, {"post_data": [{"created_at": 1554222592.0, "distinguished": null, "type": "comment", "score": 1, "id": "ejygmgq"}], "id": "SubredditDrama"}, {"post_data": [{"created_at": 1553867737.0, "distinguished": null, "type": "submission", "score": 7, "id": "b6xkgw"}, {"created_at": 1528034069.0, "distinguished": null, "type": "comment", "score": 1, "id": "e01gxk4"}, {"created_at": 1526141835.0, "distinguished": null, "type": "comment", "score": 1, "id": "dyv7p0m"}, {"created_at": 1523665843.0, "distinguished": null, "type": "comment", "score": 1, "id": "dxbwd3f"}, {"created_at": 1520992782.0, "distinguished": null, "type": "comment", "score": 10, "id": "dvnwidw"}, {"created_at": 1514150753.0, "distinguished": null, "type": "comment", "score": 20, "id": "drprq1b"}, {"created_at": 1514150741.0, "distinguished": null, "type": "comment", "score": 21, "id": "drprpo4"}, {"created_at": 1513723080.0, "distinguished": null, "type": "comment", "score": 19, "id": "drhs4ea"}, {"created_at": 1513385840.0, "distinguished": null, "type": "comment", "score": 5, "id": "drbdphj"}, {"created_at": 1511747315.0, "distinguished": null, "type": "submission", "score": 46, "id": "7frmkl"}, {"created_at": 1505761293.0, "distinguished": null, "type": "comment", "score": 3, "id": "dn6ht2z"}, {"created_at": 1505705216.0, "distinguished": null, "type": "submission", "score": 106, "id": "70ses9"}, {"created_at": 1500341599.0, "distinguished": null, "type": "comment", "score": 25, "id": "dkd0b39"}, {"created_at": 1499116787.0, "distinguished": null, "type": "submission", "score": 4, "id": "6l2qyl"}, {"created_at": 1482959093.0, "distinguished": null, "type": "comment", "score": 1, "id": "dbqachd"}, {"created_at": 1478832742.0, "distinguished": null, "type": "comment", "score": 1, "id": "d9vbib5"}], "id": "NLSSCircleJerk"}, {"post_data": [{"created_at": 1553715984.0, "distinguished": null, "type": "comment", "score": 12, "id": "ejio1jj"}], "id": "Yogscast"}, {"post_data": [{"created_at": 1553639332.0, "distinguished": null, "type": "comment", "score": 4, "id": "ejgbluv"}, {"created_at": 1553453987.0, "distinguished": null, "type": "comment", "score": 2, "id": "eja8i9z"}, {"created_at": 1553091714.0, "distinguished": null, "type": "comment", "score": 16, "id": "eiyj781"}, {"created_at": 1531502528.0, "distinguished": null, "type": "comment", "score": 2, "id": "e2bv01l"}, {"created_at": 1530904361.0, "distinguished": null, "type": "comment", "score": 1, "id": "e1wph3i"}, {"created_at": 1530387359.0, "distinguished": null, "type": "comment", "score": 1, "id": "e1kezws"}, {"created_at": 1528819717.0, "distinguished": null, "type": "comment", "score": 1, "id": "e0jr9sd"}, {"created_at": 1506299990.0, "distinguished": null, "type": "comment", "score": 1, "id": "dngpzn5"}, {"created_at": 1505609934.0, "distinguished": null, "type": "comment", "score": 2, "id": "dn3uamy"}, {"created_at": 1505520142.0, "distinguished": null, "type": "submission", "score": 8, "id": "70dr8o"}, {"created_at": 1502975800.0, "distinguished": null, "type": "comment", "score": 2, "id": "dlqzst9"}, {"created_at": 1493044294.0, "distinguished": null, "type": "comment", "score": 9, "id": "dgomqwi"}, {"created_at": 1489599659.0, "distinguished": null, "type": "comment", "score": 1, "id": "deyurw8"}], "id": "darkestdungeon"}, {"post_data": [{"created_at": 1552661762.0, "distinguished": null, "type": "comment", "score": 2, "id": "eilb0cd"}], "id": "memes"}, {"post_data": [{"created_at": 1551881969.0, "distinguished": null, "type": "comment", "score": 1, "id": "ehx0yg7"}], "id": "IllBeYourGuide"}, {"post_data": [{"created_at": 1549827646.0, "distinguished": null, "type": "comment", "score": 15, "id": "eg693tb"}], "id": "AskOuija"}, {"post_data": [{"created_at": 1549763507.0, "distinguished": null, "type": "comment", "score": 2, "id": "eg4n7qv"}], "id": "CTM"}, {"post_data": [{"created_at": 1548550478.0, "distinguished": null, "type": "comment", "score": 1, "id": "ef24vk1"}], "id": "AskMen"}, {"post_data": [{"created_at": 1548131591.0, "distinguished": null, "type": "comment", "score": 2, "id": "eeo5hud"}, {"created_at": 1548130011.0, "distinguished": null, "type": "submission", "score": 17, "id": "aiiypg"}, {"created_at": 1489353420.0, "distinguished": null, "type": "comment", "score": 1, "id": "deuepc3"}], "id": "me_irl"}, {"post_data": [{"created_at": 1547857302.0, "distinguished": null, "type": "submission", "score": 5, "id": "ahgujp"}], "id": "slaythespire"}, {"post_data": [{"created_at": 1547574704.0, "distinguished": null, "type": "comment", "score": 4, "id": "ee4ukg9"}], "id": "badMovies"}, {"post_data": [{"created_at": 1546961315.0, "distinguished": null, "type": "comment", "score": 3, "id": "edkccen"}], "id": "biomememes"}, {"post_data": [{"created_at": 1546541474.0, "distinguished": null, "type": "comment", "score": 1, "id": "ed6191x"}, {"created_at": 1546539476.0, "distinguished": null, "type": "submission", "score": 21, "id": "ac8f67"}, {"created_at": 1482200664.0, "distinguished": null, "type": "comment", "score": 2, "id": "dbenvi6"}], "id": "aww"}, {"post_data": [{"created_at": 1537456959.0, "distinguished": null, "type": "comment", "score": 3, "id": "e6bl63y"}], "id": "woahdude"}, {"post_data": [{"created_at": 1537030196.0, "distinguished": null, "type": "comment", "score": 9, "id": "e610sne"}], "id": "thomasthedankengine"}, {"post_data": [{"created_at": 1533841270.0, "distinguished": null, "type": "comment", "score": 1, "id": "e3wk3au"}, {"created_at": 1533760509.0, "distinguished": null, "type": "submission", "score": 1, "id": "95psfb"}, {"created_at": 1483824334.0, "distinguished": null, "type": "comment", "score": 7, "id": "dc4q7sg"}, {"created_at": 1428869190.0, "distinguished": null, "type": "comment", "score": 11, "id": "cqa2wul"}, {"created_at": 1426277779.0, "distinguished": null, "type": "comment", "score": 9, "id": "cpe0ff7"}, {"created_at": 1418332602.0, "distinguished": null, "type": "comment", "score": 1, "id": "cms63l9"}, {"created_at": 1415485908.0, "distinguished": null, "type": "comment", "score": 1, "id": "clwybxo"}, {"created_at": 1415467440.0, "distinguished": null, "type": "comment", "score": 1, "id": "clwq6j8"}, {"created_at": 1415313806.0, "distinguished": null, "type": "comment", "score": 1, "id": "clv5rsb"}, {"created_at": 1415310094.0, "distinguished": null, "type": "comment", "score": 1, "id": "clv3mvi"}, {"created_at": 1415310057.0, "distinguished": null, "type": "comment", "score": 1, "id": "clv3m3e"}, {"created_at": 1415137069.0, "distinguished": null, "type": "comment", "score": 1, "id": "clt16hm"}, {"created_at": 1415109206.0, "distinguished": null, "type": "comment", "score": 1, "id": "clsm9j0"}, {"created_at": 1415109158.0, "distinguished": null, "type": "comment", "score": 1, "id": "clsm8yi"}, {"created_at": 1414976620.0, "distinguished": null, "type": "comment", "score": 1, "id": "clrajs1"}, {"created_at": 1414859413.0, "distinguished": null, "type": "comment", "score": 4, "id": "clq19xy"}, {"created_at": 1414835889.0, "distinguished": null, "type": "comment", "score": 4, "id": "clpvgih"}, {"created_at": 1414511528.0, "distinguished": null, "type": "comment", "score": 3, "id": "clm7omo"}], "id": "bindingofisaac"}, {"post_data": [{"created_at": 1531254268.0, "distinguished": null, "type": "comment", "score": 1, "id": "e25elwu"}, {"created_at": 1531229043.0, "distinguished": null, "type": "comment", "score": 2, "id": "e24itxv"}, {"created_at": 1531196249.0, "distinguished": null, "type": "comment", "score": 1, "id": "e23wx4z"}, {"created_at": 1531196056.0, "distinguished": null, "type": "comment", "score": 1, "id": "e23wq81"}, {"created_at": 1530919421.0, "distinguished": null, "type": "comment", "score": 1, "id": "e1x73c6"}, {"created_at": 1530919185.0, "distinguished": null, "type": "comment", "score": 1, "id": "e1x6uxe"}], "id": "thanosdidnothingwrong"}, {"post_data": [{"created_at": 1530107837.0, "distinguished": null, "type": "comment", "score": 1, "id": "e1dm9f6"}, {"created_at": 1445365465.0, "distinguished": null, "type": "comment", "score": 1, "id": "cw6ngv0"}], "id": "AskReddit"}, {"post_data": [{"created_at": 1528589452.0, "distinguished": null, "type": "comment", "score": 1, "id": "e0ep277"}], "id": "IASIP"}, {"post_data": [{"created_at": 1527862717.0, "distinguished": null, "type": "comment", "score": 2, "id": "dzxvvdn"}], "id": "webcomics"}, {"post_data": [{"created_at": 1527395037.0, "distinguished": null, "type": "comment", "score": 3, "id": "dzn6zb2"}, {"created_at": 1526828223.0, "distinguished": null, "type": "comment", "score": 2, "id": "dza9m7r"}], "id": "meirl"}, {"post_data": [{"created_at": 1527260412.0, "distinguished": null, "type": "comment", "score": 1, "id": "dzk7qvb"}, {"created_at": 1527108405.0, "distinguished": null, "type": "comment", "score": 19, "id": "dzgr7wr"}], "id": "rarepuppers"}, {"post_data": [{"created_at": 1525584723.0, "distinguished": null, "type": "comment", "score": 1, "id": "dyiwv30"}], "id": "firstworldanarchists"}, {"post_data": [{"created_at": 1524143727.0, "distinguished": null, "type": "comment", "score": 1, "id": "dxmg2d9"}, {"created_at": 1524112357.0, "distinguished": null, "type": "comment", "score": 0, "id": "dxlz0tc"}], "id": "BlackPeopleTwitter"}, {"post_data": [{"created_at": 1522770428.0, "distinguished": null, "type": "comment", "score": 1, "id": "dwqhide"}, {"created_at": 1522721966.0, "distinguished": null, "type": "submission", "score": 1, "id": "897uy8"}], "id": "CircleofTrust"}, {"post_data": [{"created_at": 1520954908.0, "distinguished": null, "type": "comment", "score": 6, "id": "dvms6t0"}], "id": "starterpacks"}, {"post_data": [{"created_at": 1520452805.0, "distinguished": null, "type": "comment", "score": 1, "id": "dvc66zf"}], "id": "MBMBAM"}, {"post_data": [{"created_at": 1517850949.0, "distinguished": null, "type": "comment", "score": 4, "id": "dtrzt2i"}], "id": "news"}, {"post_data": [{"created_at": 1515824486.0, "distinguished": null, "type": "comment", "score": 1, "id": "dslzet8"}], "id": "garlicoin"}, {"post_data": [{"created_at": 1515727925.0, "distinguished": null, "type": "comment", "score": 26, "id": "dsjzt80"}, {"created_at": 1515712037.0, "distinguished": null, "type": "comment", "score": 96, "id": "dsjlpx7"}], "id": "calvinandhobbes"}, {"post_data": [{"created_at": 1515557164.0, "distinguished": null, "type": "comment", "score": 1, "id": "dsgblwe"}], "id": "depression"}, {"post_data": [{"created_at": 1514622928.0, "distinguished": null, "type": "comment", "score": 1, "id": "dry3sa9"}, {"created_at": 1512925335.0, "distinguished": null, "type": "comment", "score": 7, "id": "dr1k581"}, {"created_at": 1512925286.0, "distinguished": null, "type": "submission", "score": 49, "id": "7iv248"}], "id": "thehedgehog"}, {"post_data": [{"created_at": 1513978521.0, "distinguished": null, "type": "submission", "score": 3, "id": "7lkg6c"}, {"created_at": 1502906741.0, "distinguished": null, "type": "comment", "score": 2, "id": "dlpou5v"}, {"created_at": 1488904463.0, "distinguished": null, "type": "comment", "score": 1, "id": "demfnnc"}], "id": "CoolGamesInc"}, {"post_data": [{"created_at": 1512269993.0, "distinguished": null, "type": "comment", "score": 1, "id": "dqoogz7"}], "id": "GarlicBreadMemes"}, {"post_data": [{"created_at": 1509823117.0, "distinguished": null, "type": "submission", "score": 1, "id": "7asnxm"}, {"created_at": 1509689235.0, "distinguished": null, "type": "comment", "score": 1, "id": "dpa0ll5"}, {"created_at": 1509689219.0, "distinguished": null, "type": "comment", "score": 1, "id": "dpa0lcb"}, {"created_at": 1509689117.0, "distinguished": null, "type": "submission", "score": 1, "id": "7ahkry"}], "id": "HolstenEdel"}, {"post_data": [{"created_at": 1509417755.0, "distinguished": null, "type": "comment", "score": 1, "id": "dp4jml5"}, {"created_at": 1477955290.0, "distinguished": null, "type": "comment", "score": 1, "id": "d9g2yad"}, {"created_at": 1477955247.0, "distinguished": null, "type": "comment", "score": 1, "id": "d9g2x7k"}, {"created_at": 1477930271.0, "distinguished": null, "type": "comment", "score": 1, "id": "d9fhps1"}], "id": "pokemon"}, {"post_data": [{"created_at": 1508693124.0, "distinguished": null, "type": "comment", "score": 5, "id": "doq8vvu"}], "id": "Gamingcirclejerk"}, {"post_data": [{"created_at": 1507210889.0, "distinguished": null, "type": "comment", "score": 2, "id": "dnxxkra"}, {"created_at": 1502714885.0, "distinguished": null, "type": "comment", "score": 2, "id": "dllouze"}, {"created_at": 1485709144.0, "distinguished": null, "type": "comment", "score": 1, "id": "dd27vpu"}], "id": "WebGames"}, {"post_data": [{"created_at": 1505667913.0, "distinguished": null, "type": "comment", "score": 3, "id": "dn4pzuo"}], "id": "WritingPrompts"}, {"post_data": [{"created_at": 1502972513.0, "distinguished": null, "type": "comment", "score": 12, "id": "dlqxmae"}, {"created_at": 1502944188.0, "distinguished": null, "type": "comment", "score": 11, "id": "dlqkqsl"}, {"created_at": 1502886969.0, "distinguished": null, "type": "comment", "score": 45, "id": "dlp6s87"}], "id": "beholdthemasterrace"}, {"post_data": [{"created_at": 1502428634.0, "distinguished": null, "type": "comment", "score": 1, "id": "dlgnq24"}], "id": "u_iceboob"}, {"post_data": [{"created_at": 1502394300.0, "distinguished": null, "type": "comment", "score": 1, "id": "dlfw9mh"}], "id": "silhouWHAT"}, {"post_data": [{"created_at": 1502205828.0, "distinguished": null, "type": "comment", "score": 3, "id": "dlc0bfk"}], "id": "4chan"}, {"post_data": [{"created_at": 1502139528.0, "distinguished": null, "type": "comment", "score": 1, "id": "dlau1cd"}, {"created_at": 1501777948.0, "distinguished": null, "type": "comment", "score": 1, "id": "dl46apn"}, {"created_at": 1501736055.0, "distinguished": null, "type": "comment", "score": 9, "id": "dl3hnh8"}, {"created_at": 1501735858.0, "distinguished": null, "type": "comment", "score": 2, "id": "dl3hjfv"}, {"created_at": 1501692123.0, "distinguished": null, "type": "comment", "score": 1, "id": "dl2f61f"}, {"created_at": 1501680090.0, "distinguished": null, "type": "comment", "score": 1, "id": "dl249vd"}, {"created_at": 1501679924.0, "distinguished": null, "type": "submission", "score": 5, "id": "6r43m5"}], "id": "Lovecraft"}, {"post_data": [{"created_at": 1501692059.0, "distinguished": null, "type": "comment", "score": 2, "id": "dl2f3s7"}], "id": "ComedyCemetery"}, {"post_data": [{"created_at": 1501681659.0, "distinguished": null, "type": "comment", "score": 2, "id": "dl25hbh"}], "id": "dataisbeautiful"}, {"post_data": [{"created_at": 1501106562.0, "distinguished": null, "type": "comment", "score": 2, "id": "dkrlo7o"}, {"created_at": 1501106529.0, "distinguished": null, "type": "comment", "score": 6, "id": "dkrln5a"}, {"created_at": 1501095639.0, "distinguished": null, "type": "comment", "score": 1, "id": "dkrb6kz"}, {"created_at": 1501087795.0, "distinguished": null, "type": "comment", "score": 11, "id": "dkr343k"}, {"created_at": 1501085765.0, "distinguished": null, "type": "comment", "score": 9, "id": "dkr10cl"}], "id": "IncelTears"}, {"post_data": [{"created_at": 1494338786.0, "distinguished": null, "type": "comment", "score": 2, "id": "dhbu6lz"}, {"created_at": 1478978346.0, "distinguished": null, "type": "comment", "score": 1, "id": "d9xgzny"}], "id": "Terraria"}, {"post_data": [{"created_at": 1485006284.0, "distinguished": null, "type": "comment", "score": 1, "id": "dcpoc6q"}], "id": "millionairemakers"}, {"post_data": [{"created_at": 1481507644.0, "distinguished": null, "type": "comment", "score": 2, "id": "db2xtq5"}], "id": "youtubehaiku"}, {"post_data": [{"created_at": 1479862184.0, "distinguished": null, "type": "comment", "score": 4, "id": "dabsgqi"}], "id": "skyrim"}, {"post_data": [{"created_at": 1479743588.0, "distinguished": null, "type": "comment", "score": 1, "id": "da9lwo7"}], "id": "pics"}, {"post_data": [{"created_at": 1449433878.0, "distinguished": null, "type": "comment", "score": 3, "id": "cxpfihq"}], "id": "ledootgeneration"}, {"post_data": [{"created_at": 1432997868.0, "distinguished": null, "type": "comment", "score": 1, "id": "crpx1cj"}], "id": "ShittyFanTheories"}, {"post_data": [{"created_at": 1432406821.0, "distinguished": null, "type": "submission", "score": 9, "id": "370hmz"}], "id": "funny"}, {"post_data": [{"created_at": 1430091571.0, "distinguished": null, "type": "comment", "score": 1, "id": "cqpoiyt"}, {"created_at": 1428009760.0, "distinguished": null, "type": "comment", "score": 1, "id": "cpzay21"}, {"created_at": 1428009738.0, "distinguished": null, "type": "submission", "score": 1, "id": "318kkn"}], "id": "thebutton"}, {"post_data": [{"created_at": 1429178643.0, "distinguished": null, "type": "comment", "score": 1, "id": "cqe6h5v"}, {"created_at": 1429178614.0, "distinguished": null, "type": "comment", "score": 1, "id": "cqe6gxj"}], "id": "circlejerk"}, {"post_data": [{"created_at": 1428343249.0, "distinguished": null, "type": "comment", "score": 3, "id": "cq35v1b"}], "id": "AdviceAnimals"}, {"post_data": [{"created_at": 1402416545.0, "distinguished": null, "type": "comment", "score": 155, "id": "ci3yfd5"}], "id": "explainlikeimfive"}], "links": [{"time_delta": [913030.0], "count": 1, "source": "northernlion", "target": "firstworldanarchists"}, {"time_delta": [818978.0], "count": 1, "source": "northernlion", "target": "CircleofTrust"}, {"time_delta": [42717.0], "count": 1, "source": "northernlion", "target": "northernlion"}, {"time_delta": [1963317.0], "count": 1, "source": "northernlion", "target": "MBMBAM"}, {"time_delta": [392537.0], "count": 1, "source": "northernlion", "target": "pokemon"}, {"time_delta": [19340.0], "count": 1, "source": "northernlion", "target": "u_iceboob"}, {"time_delta": [837874.0], "count": 1, "source": "SubredditDrama", "target": "northernlion"}, {"time_delta": [354855.0], "count": 1, "source": "NLSSCircleJerk", "target": "SubredditDrama"}, {"time_delta": [555383.0], "count": 1, "source": "NLSSCircleJerk", "target": "IASIP"}, {"time_delta": [686388.0], "count": 1, "source": "NLSSCircleJerk", "target": "meirl"}, {"time_delta": [446514.0], "count": 1, "source": "NLSSCircleJerk", "target": "BlackPeopleTwitter"}, {"time_delta": [867489.0], "count": 1, "source": "NLSSCircleJerk", "target": "northernlion"}, {"time_delta": [472175.0], "count": 1, "source": "NLSSCircleJerk", "target": "thehedgehog"}, {"time_delta": [12.0, 337240.0, 56077.0, 1224812.0], "count": 4, "source": "NLSSCircleJerk", "target": "NLSSCircleJerk"}, {"time_delta": [255441.0], "count": 1, "source": "NLSSCircleJerk", "target": "CoolGamesInc"}, {"time_delta": [522678.0], "count": 1, "source": "NLSSCircleJerk", "target": "GarlicBreadMemes"}, {"time_delta": [538697.0], "count": 1, "source": "NLSSCircleJerk", "target": "darkestdungeon"}, {"time_delta": [744166.0], "count": 1, "source": "NLSSCircleJerk", "target": "IncelTears"}, {"time_delta": [865241.0], "count": 1, "source": "NLSSCircleJerk", "target": "bindingofisaac"}, {"time_delta": [145604.0], "count": 1, "source": "NLSSCircleJerk", "target": "Terraria"}, {"time_delta": [151753.0], "count": 1, "source": "Yogscast", "target": "NLSSCircleJerk"}, {"time_delta": [76652.0], "count": 1, "source": "darkestdungeon", "target": "Yogscast"}, {"time_delta": [185345.0, 362273.0, 517002.0, 89792.0, 2544342.0, 3444635.0], "count": 6, "source": "darkestdungeon", "target": "darkestdungeon"}, {"time_delta": [2257981.0], "count": 1, "source": "darkestdungeon", "target": "bindingofisaac"}, {"time_delta": [14824.0], "count": 1, "source": "darkestdungeon", "target": "thanosdidnothingwrong"}, {"time_delta": [1288120.0], "count": 1, "source": "darkestdungeon", "target": "AskReddit"}, {"time_delta": [910899.0], "count": 1, "source": "darkestdungeon", "target": "WebGames"}, {"time_delta": [57979.0], "count": 1, "source": "darkestdungeon", "target": "WritingPrompts"}, {"time_delta": [1294492.0], "count": 1, "source": "darkestdungeon", "target": "Terraria"}, {"time_delta": [429952.0], "count": 1, "source": "memes", "target": "darkestdungeon"}, {"time_delta": [779793.0], "count": 1, "source": "IllBeYourGuide", "target": "memes"}, {"time_delta": [2054323.0], "count": 1, "source": "AskOuija", "target": "IllBeYourGuide"}, {"time_delta": [64139.0], "count": 1, "source": "CTM", "target": "AskOuija"}, {"time_delta": [1213029.0], "count": 1, "source": "AskMen", "target": "CTM"}, {"time_delta": [418887.0], "count": 1, "source": "me_irl", "target": "AskMen"}, {"time_delta": [1580.0], "count": 1, "source": "me_irl", "target": "me_irl"}, {"time_delta": [246239.0], "count": 1, "source": "me_irl", "target": "darkestdungeon"}, {"time_delta": [272709.0], "count": 1, "source": "slaythespire", "target": "me_irl"}, {"time_delta": [282598.0], "count": 1, "source": "badMovies", "target": "slaythespire"}, {"time_delta": [613389.0], "count": 1, "source": "biomememes", "target": "badMovies"}, {"time_delta": [419841.0], "count": 1, "source": "aww", "target": "biomememes"}, {"time_delta": [1998.0], "count": 1, "source": "aww", "target": "aww"}, {"time_delta": [758429.0], "count": 1, "source": "aww", "target": "NLSSCircleJerk"}, {"time_delta": [9082517.0], "count": 1, "source": "woahdude", "target": "aww"}, {"time_delta": [426763.0], "count": 1, "source": "thomasthedankengine", "target": "woahdude"}, {"time_delta": [3188926.0], "count": 1, "source": "bindingofisaac", "target": "thomasthedankengine"}, {"time_delta": [80761.0, 7945177.0, 2846694.0, 18468.0, 153634.0, 3712.0, 37.0, 172988.0, 27863.0, 48.0, 132538.0, 117207.0, 23524.0, 324361.0], "count": 14, "source": "bindingofisaac", "target": "bindingofisaac"}, {"time_delta": [1181950.0], "count": 1, "source": "bindingofisaac", "target": "millionairemakers"}, {"time_delta": [309424.0], "count": 1, "source": "bindingofisaac", "target": "circlejerk"}, {"time_delta": [1731959.0], "count": 1, "source": "bindingofisaac", "target": "thebutton"}, {"time_delta": [248260.0], "count": 1, "source": "thanosdidnothingwrong", "target": "darkestdungeon"}, {"time_delta": [25225.0, 32794.0, 193.0, 276635.0, 236.0], "count": 5, "source": "thanosdidnothingwrong", "target": "thanosdidnothingwrong"}, {"time_delta": [279522.0], "count": 1, "source": "AskReddit", "target": "darkestdungeon"}, {"time_delta": [4068413.0], "count": 1, "source": "AskReddit", "target": "ledootgeneration"}, {"time_delta": [230265.0], "count": 1, "source": "IASIP", "target": "darkestdungeon"}, {"time_delta": [171352.0], "count": 1, "source": "webcomics", "target": "NLSSCircleJerk"}, {"time_delta": [467680.0], "count": 1, "source": "meirl", "target": "webcomics"}, {"time_delta": [280182.0], "count": 1, "source": "meirl", "target": "rarepuppers"}, {"time_delta": [134625.0], "count": 1, "source": "rarepuppers", "target": "meirl"}, {"time_delta": [152007.0], "count": 1, "source": "rarepuppers", "target": "rarepuppers"}, {"time_delta": [557112.0], "count": 1, "source": "firstworldanarchists", "target": "NLSSCircleJerk"}, {"time_delta": [527966.0], "count": 1, "source": "BlackPeopleTwitter", "target": "northernlion"}, {"time_delta": [31370.0], "count": 1, "source": "BlackPeopleTwitter", "target": "BlackPeopleTwitter"}, {"time_delta": [895415.0], "count": 1, "source": "CircleofTrust", "target": "NLSSCircleJerk"}, {"time_delta": [48462.0], "count": 1, "source": "CircleofTrust", "target": "CircleofTrust"}, {"time_delta": [37874.0], "count": 1, "source": "starterpacks", "target": "NLSSCircleJerk"}, {"time_delta": [502103.0], "count": 1, "source": "MBMBAM", "target": "starterpacks"}, {"time_delta": [638539.0], "count": 1, "source": "news", "target": "northernlion"}, {"time_delta": [2026463.0], "count": 1, "source": "garlicoin", "target": "news"}, {"time_delta": [96561.0], "count": 1, "source": "calvinandhobbes", "target": "garlicoin"}, {"time_delta": [15888.0], "count": 1, "source": "calvinandhobbes", "target": "calvinandhobbes"}, {"time_delta": [154873.0], "count": 1, "source": "depression", "target": "calvinandhobbes"}, {"time_delta": [934236.0], "count": 1, "source": "thehedgehog", "target": "depression"}, {"time_delta": [460505.0], "count": 1, "source": "thehedgehog", "target": "NLSSCircleJerk"}, {"time_delta": [49.0], "count": 1, "source": "thehedgehog", "target": "thehedgehog"}, {"time_delta": [172220.0], "count": 1, "source": "CoolGamesInc", "target": "NLSSCircleJerk"}, {"time_delta": [37447.0], "count": 1, "source": "CoolGamesInc", "target": "beholdthemasterrace"}, {"time_delta": [448957.0], "count": 1, "source": "CoolGamesInc", "target": "me_irl"}, {"time_delta": [655293.0], "count": 1, "source": "GarlicBreadMemes", "target": "thehedgehog"}, {"time_delta": [1924198.0], "count": 1, "source": "HolstenEdel", "target": "NLSSCircleJerk"}, {"time_delta": [133882.0, 16.0, 102.0], "count": 3, "source": "HolstenEdel", "target": "HolstenEdel"}, {"time_delta": [271362.0], "count": 1, "source": "pokemon", "target": "HolstenEdel"}, {"time_delta": [877452.0], "count": 1, "source": "pokemon", "target": "NLSSCircleJerk"}, {"time_delta": [43.0, 24976.0], "count": 2, "source": "pokemon", "target": "pokemon"}, {"time_delta": [332094.0], "count": 1, "source": "Gamingcirclejerk", "target": "northernlion"}, {"time_delta": [1482235.0], "count": 1, "source": "WebGames", "target": "Gamingcirclejerk"}, {"time_delta": [172084.0], "count": 1, "source": "WebGames", "target": "beholdthemasterrace"}, {"time_delta": [3195319.0], "count": 1, "source": "WebGames", "target": "CoolGamesInc"}, {"time_delta": [37303.0], "count": 1, "source": "WritingPrompts", "target": "NLSSCircleJerk"}, {"time_delta": [3287.0], "count": 1, "source": "beholdthemasterrace", "target": "darkestdungeon"}, {"time_delta": [28325.0], "count": 1, "source": "beholdthemasterrace", "target": "beholdthemasterrace"}, {"time_delta": [19772.0], "count": 1, "source": "beholdthemasterrace", "target": "CoolGamesInc"}, {"time_delta": [286251.0], "count": 1, "source": "u_iceboob", "target": "WebGames"}, {"time_delta": [14994.0], "count": 1, "source": "silhouWHAT", "target": "northernlion"}, {"time_delta": [188472.0], "count": 1, "source": "4chan", "target": "silhouWHAT"}, {"time_delta": [66300.0], "count": 1, "source": "Lovecraft", "target": "4chan"}, {"time_delta": [361580.0, 41893.0, 197.0, 43735.0, 166.0], "count": 5, "source": "Lovecraft", "target": "Lovecraft"}, {"time_delta": [1569.0], "count": 1, "source": "Lovecraft", "target": "dataisbeautiful"}, {"time_delta": [64.0], "count": 1, "source": "ComedyCemetery", "target": "Lovecraft"}, {"time_delta": [10400.0], "count": 1, "source": "dataisbeautiful", "target": "ComedyCemetery"}, {"time_delta": [573362.0], "count": 1, "source": "IncelTears", "target": "Lovecraft"}, {"time_delta": [33.0, 10890.0, 7844.0, 2030.0], "count": 4, "source": "IncelTears", "target": "IncelTears"}, {"time_delta": [4778001.0], "count": 1, "source": "Terraria", "target": "NLSSCircleJerk"}, {"time_delta": [765242.0], "count": 1, "source": "Terraria", "target": "pics"}, {"time_delta": [702860.0], "count": 1, "source": "millionairemakers", "target": "WebGames"}, {"time_delta": [693020.0], "count": 1, "source": "youtubehaiku", "target": "aww"}, {"time_delta": [1645460.0], "count": 1, "source": "skyrim", "target": "youtubehaiku"}, {"time_delta": [118596.0], "count": 1, "source": "pics", "target": "skyrim"}, {"time_delta": [28496393.0], "count": 1, "source": "ledootgeneration", "target": "pokemon"}, {"time_delta": [12367597.0], "count": 1, "source": "ShittyFanTheories", "target": "AskReddit"}, {"time_delta": [591047.0], "count": 1, "source": "funny", "target": "ShittyFanTheories"}, {"time_delta": [2315250.0], "count": 1, "source": "thebutton", "target": "funny"}, {"time_delta": [333489.0], "count": 1, "source": "thebutton", "target": "AdviceAnimals"}, {"time_delta": [22.0], "count": 1, "source": "thebutton", "target": "thebutton"}, {"time_delta": [912928.0], "count": 1, "source": "circlejerk", "target": "thebutton"}, {"time_delta": [29.0], "count": 1, "source": "circlejerk", "target": "circlejerk"}, {"time_delta": [525941.0], "count": 1, "source": "AdviceAnimals", "target": "bindingofisaac"}, {"time_delta": [12094983.0], "count": 1, "source": "explainlikeimfive", "target": "bindingofisaac"}]}}