{"user": "e699e1e2ae432f814115fed33e34b22e989a96d0", "user_type": "random_user", "data": {"directed": true, "multigraph": false, "graph": {}, "nodes": [{"post_data": [{"created_at": 1555493980.0, "distinguished": null, "type": "comment", "score": 1, "id": "el38etb"}, {"created_at": 1555492678.0, "distinguished": null, "type": "comment", "score": 1, "id": "el37n4e"}, {"created_at": 1555488850.0, "distinguished": null, "type": "comment", "score": 1, "id": "el35g3z"}, {"created_at": 1555468557.0, "distinguished": null, "type": "comment", "score": 19, "id": "el2mgju"}, {"created_at": 1555466778.0, "distinguished": null, "type": "comment", "score": 3, "id": "el2k1vm"}, {"created_at": 1555466645.0, "distinguished": null, "type": "comment", "score": 3, "id": "el2jvbm"}, {"created_at": 1555466387.0, "distinguished": null, "type": "comment", "score": 1, "id": "el2ji47"}, {"created_at": 1555466238.0, "distinguished": null, "type": "comment", "score": 7, "id": "el2ja5l"}, {"created_at": 1555466114.0, "distinguished": null, "type": "comment", "score": 5, "id": "el2j3d3"}, {"created_at": 1555465817.0, "distinguished": null, "type": "comment", "score": 2, "id": "el2inkp"}, {"created_at": 1555465649.0, "distinguished": null, "type": "comment", "score": 2, "id": "el2ieff"}, {"created_at": 1555465424.0, "distinguished": null, "type": "comment", "score": 2, "id": "el2i1jy"}, {"created_at": 1555465243.0, "distinguished": null, "type": "comment", "score": 1, "id": "el2hrgz"}, {"created_at": 1555465201.0, "distinguished": null, "type": "comment", "score": 1, "id": "el2hp6x"}, {"created_at": 1555465085.0, "distinguished": null, "type": "comment", "score": 5, "id": "el2hity"}, {"created_at": 1555464623.0, "distinguished": null, "type": "comment", "score": 2, "id": "el2guwu"}, {"created_at": 1555463733.0, "distinguished": null, "type": "comment", "score": 6, "id": "el2fneq"}, {"created_at": 1555463663.0, "distinguished": null, "type": "comment", "score": 5, "id": "el2fk2k"}, {"created_at": 1555463194.0, "distinguished": null, "type": "comment", "score": 1, "id": "el2ex0m"}, {"created_at": 1555463027.0, "distinguished": null, "type": "comment", "score": 3, "id": "el2eoh9"}, {"created_at": 1555462968.0, "distinguished": null, "type": "comment", "score": 1, "id": "el2eljj"}, {"created_at": 1555462926.0, "distinguished": null, "type": "comment", "score": 2, "id": "el2ejbt"}, {"created_at": 1555462887.0, "distinguished": null, "type": "comment", "score": 1, "id": "el2ehe3"}, {"created_at": 1555462742.0, "distinguished": null, "type": "comment", "score": 1, "id": "el2eada"}, {"created_at": 1555462693.0, "distinguished": null, "type": "comment", "score": 2, "id": "el2e7z3"}, {"created_at": 1555462560.0, "distinguished": null, "type": "comment", "score": 18, "id": "el2e1cm"}, {"created_at": 1555462136.0, "distinguished": null, "type": "comment", "score": 5, "id": "el2dg2a"}, {"created_at": 1555461960.0, "distinguished": null, "type": "comment", "score": 1, "id": "el2d7ac"}, {"created_at": 1555461785.0, "distinguished": null, "type": "comment", "score": 1, "id": "el2cymd"}, {"created_at": 1555461620.0, "distinguished": null, "type": "comment", "score": 2, "id": "el2cqjy"}, {"created_at": 1555461478.0, "distinguished": null, "type": "comment", "score": 1, "id": "el2cjsx"}, {"created_at": 1555461428.0, "distinguished": null, "type": "comment", "score": 1, "id": "el2chch"}, {"created_at": 1555461324.0, "distinguished": null, "type": "comment", "score": 4, "id": "el2ccf7"}, {"created_at": 1555461304.0, "distinguished": null, "type": "comment", "score": 1, "id": "el2cbdp"}, {"created_at": 1555461101.0, "distinguished": null, "type": "comment", "score": 24, "id": "el2c1hb"}, {"created_at": 1555460762.0, "distinguished": null, "type": "comment", "score": 1, "id": "el2bl7f"}, {"created_at": 1555460634.0, "distinguished": null, "type": "comment", "score": 2, "id": "el2besr"}, {"created_at": 1555460571.0, "distinguished": null, "type": "comment", "score": 1, "id": "el2bbpg"}, {"created_at": 1555460380.0, "distinguished": null, "type": "comment", "score": 1, "id": "el2b200"}, {"created_at": 1555459837.0, "distinguished": null, "type": "comment", "score": 1, "id": "el2ab98"}, {"created_at": 1555459432.0, "distinguished": null, "type": "comment", "score": 5, "id": "el29s3o"}, {"created_at": 1555458849.0, "distinguished": null, "type": "comment", "score": 2, "id": "el290xy"}, {"created_at": 1555458753.0, "distinguished": null, "type": "comment", "score": 7, "id": "el28wdu"}, {"created_at": 1555458389.0, "distinguished": null, "type": "comment", "score": 4, "id": "el28eu7"}, {"created_at": 1555458259.0, "distinguished": null, "type": "comment", "score": 4, "id": "el288hn"}, {"created_at": 1555452537.0, "distinguished": null, "type": "comment", "score": 29, "id": "el20ic8"}, {"created_at": 1555440629.0, "distinguished": null, "type": "comment", "score": 56, "id": "el1hadv"}, {"created_at": 1555439493.0, "distinguished": null, "type": "comment", "score": 1, "id": "el1fdwh"}, {"created_at": 1555393554.0, "distinguished": null, "type": "comment", "score": 3, "id": "el01uug"}, {"created_at": 1555393421.0, "distinguished": null, "type": "comment", "score": 3, "id": "el01qrs"}, {"created_at": 1555392879.0, "distinguished": null, "type": "comment", "score": 51, "id": "el019or"}, {"created_at": 1555389276.0, "distinguished": null, "type": "comment", "score": 22, "id": "ekzxw7l"}, {"created_at": 1555378411.0, "distinguished": null, "type": "comment", "score": 94, "id": "ekzkezx"}, {"created_at": 1555370095.0, "distinguished": null, "type": "comment", "score": 1, "id": "ekz90e7"}, {"created_at": 1555367221.0, "distinguished": null, "type": "comment", "score": 10, "id": "ekz4srz"}, {"created_at": 1555363467.0, "distinguished": null, "type": "comment", "score": 25, "id": "ekyz66w"}, {"created_at": 1555360318.0, "distinguished": null, "type": "comment", "score": 3, "id": "ekyw4zs"}, {"created_at": 1555347516.0, "distinguished": null, "type": "comment", "score": -2, "id": "ekyb40t"}, {"created_at": 1555341457.0, "distinguished": null, "type": "comment", "score": 19, "id": "eky1mk5"}, {"created_at": 1555340884.0, "distinguished": null, "type": "comment", "score": 1, "id": "eky0sn3"}, {"created_at": 1555335247.0, "distinguished": null, "type": "comment", "score": 1, "id": "ekxt92e"}, {"created_at": 1555333856.0, "distinguished": null, "type": "comment", "score": 3, "id": "ekxrklc"}, {"created_at": 1555333411.0, "distinguished": null, "type": "comment", "score": 9, "id": "ekxr2ri"}, {"created_at": 1555331879.0, "distinguished": null, "type": "comment", "score": 4, "id": "ekxpgto"}, {"created_at": 1555327960.0, "distinguished": null, "type": "comment", "score": 14, "id": "ekxlzcm"}, {"created_at": 1555314412.0, "distinguished": null, "type": "comment", "score": 6, "id": "ekxdymw"}, {"created_at": 1555307405.0, "distinguished": null, "type": "submission", "score": 5, "id": "bdckem"}, {"created_at": 1555301906.0, "distinguished": null, "type": "comment", "score": 70, "id": "ekx4jow"}, {"created_at": 1555293793.0, "distinguished": null, "type": "comment", "score": 2, "id": "ekwuxk8"}, {"created_at": 1555286242.0, "distinguished": null, "type": "comment", "score": 34, "id": "ekwm5fp"}, {"created_at": 1555285092.0, "distinguished": null, "type": "comment", "score": 30, "id": "ekwks26"}, {"created_at": 1555283356.0, "distinguished": null, "type": "comment", "score": 21, "id": "ekwiqqd"}, {"created_at": 1555276586.0, "distinguished": null, "type": "comment", "score": 27, "id": "ekwaeyh"}, {"created_at": 1555224435.0, "distinguished": null, "type": "comment", "score": 22, "id": "ekuugn5"}, {"created_at": 1555224093.0, "distinguished": null, "type": "comment", "score": 9, "id": "ekuu80u"}, {"created_at": 1555223730.0, "distinguished": null, "type": "comment", "score": 4, "id": "ekutyqx"}, {"created_at": 1555210187.0, "distinguished": null, "type": "comment", "score": 2, "id": "ekug9dy"}, {"created_at": 1555199501.0, "distinguished": null, "type": "comment", "score": 2, "id": "eku36oo"}, {"created_at": 1555199159.0, "distinguished": null, "type": "comment", "score": 2, "id": "eku2qvw"}, {"created_at": 1555199056.0, "distinguished": null, "type": "comment", "score": 1, "id": "eku2m4u"}, {"created_at": 1555198905.0, "distinguished": null, "type": "comment", "score": 2, "id": "eku2f33"}, {"created_at": 1555198655.0, "distinguished": null, "type": "comment", "score": 1, "id": "eku22p6"}, {"created_at": 1555198584.0, "distinguished": null, "type": "comment", "score": 5, "id": "eku1yof"}, {"created_at": 1555198380.0, "distinguished": null, "type": "comment", "score": 6, "id": "eku1nbx"}, {"created_at": 1555198313.0, "distinguished": null, "type": "comment", "score": 12, "id": "eku1jk9"}, {"created_at": 1555198243.0, "distinguished": null, "type": "comment", "score": 1, "id": "eku1flq"}, {"created_at": 1555198114.0, "distinguished": null, "type": "comment", "score": 1, "id": "eku18i7"}, {"created_at": 1555198041.0, "distinguished": null, "type": "comment", "score": 1, "id": "eku14jk"}, {"created_at": 1555197723.0, "distinguished": null, "type": "comment", "score": 4, "id": "eku0o2e"}, {"created_at": 1555197131.0, "distinguished": null, "type": "comment", "score": 1, "id": "ektzt85"}, {"created_at": 1555196779.0, "distinguished": null, "type": "comment", "score": 3, "id": "ektzawe"}, {"created_at": 1555196591.0, "distinguished": null, "type": "comment", "score": 2, "id": "ektz1ej"}, {"created_at": 1555196411.0, "distinguished": null, "type": "comment", "score": 6, "id": "ektyrxa"}, {"created_at": 1555196350.0, "distinguished": null, "type": "comment", "score": 2, "id": "ektyop6"}, {"created_at": 1555196248.0, "distinguished": null, "type": "comment", "score": 2, "id": "ektyjk9"}, {"created_at": 1555196153.0, "distinguished": null, "type": "comment", "score": 2, "id": "ektyeri"}, {"created_at": 1555196030.0, "distinguished": null, "type": "comment", "score": 3, "id": "ekty85r"}, {"created_at": 1555194860.0, "distinguished": null, "type": "comment", "score": 7, "id": "ektwi9s"}, {"created_at": 1555194746.0, "distinguished": null, "type": "comment", "score": 2, "id": "ektwcp9"}, {"created_at": 1555194608.0, "distinguished": null, "type": "comment", "score": 2, "id": "ektw6cn"}, {"created_at": 1555194034.0, "distinguished": null, "type": "comment", "score": 6, "id": "ektvflk"}, {"created_at": 1555193591.0, "distinguished": null, "type": "comment", "score": 4, "id": "ektutut"}, {"created_at": 1555193219.0, "distinguished": null, "type": "comment", "score": 4, "id": "ektuc6v"}, {"created_at": 1555192438.0, "distinguished": null, "type": "comment", "score": 6, "id": "ektt8sp"}, {"created_at": 1555192093.0, "distinguished": null, "type": "comment", "score": 2, "id": "ektss26"}, {"created_at": 1555191315.0, "distinguished": null, "type": "comment", "score": 1, "id": "ektromf"}, {"created_at": 1555190615.0, "distinguished": null, "type": "comment", "score": 1, "id": "ektqnm7"}, {"created_at": 1555190478.0, "distinguished": null, "type": "comment", "score": 3, "id": "ektqfq1"}, {"created_at": 1555190391.0, "distinguished": null, "type": "comment", "score": 1, "id": "ektqatt"}, {"created_at": 1555190341.0, "distinguished": null, "type": "comment", "score": 1, "id": "ektq7zd"}, {"created_at": 1555190176.0, "distinguished": null, "type": "comment", "score": 2, "id": "ektpyr5"}, {"created_at": 1555190062.0, "distinguished": null, "type": "comment", "score": 6, "id": "ektpsin"}, {"created_at": 1555189589.0, "distinguished": null, "type": "comment", "score": 5, "id": "ektp2nr"}, {"created_at": 1555189451.0, "distinguished": null, "type": "comment", "score": 2, "id": "ektov7x"}, {"created_at": 1555180904.0, "distinguished": null, "type": "comment", "score": 1, "id": "ektbvs1"}, {"created_at": 1555180483.0, "distinguished": null, "type": "comment", "score": 5, "id": "ektb9b8"}, {"created_at": 1555134848.0, "distinguished": null, "type": "comment", "score": 11, "id": "eks3bpm"}, {"created_at": 1555132575.0, "distinguished": null, "type": "comment", "score": 8, "id": "eks1c4r"}, {"created_at": 1555129000.0, "distinguished": null, "type": "comment", "score": 21, "id": "ekrxzhn"}, {"created_at": 1555114136.0, "distinguished": null, "type": "comment", "score": 2, "id": "ekrg92k"}, {"created_at": 1555113750.0, "distinguished": null, "type": "comment", "score": 7, "id": "ekrfqov"}, {"created_at": 1555113240.0, "distinguished": null, "type": "comment", "score": 2, "id": "ekrf1d8"}, {"created_at": 1555109313.0, "distinguished": null, "type": "comment", "score": 8, "id": "ekr9gsa"}, {"created_at": 1555095106.0, "distinguished": null, "type": "comment", "score": 2, "id": "ekqm5h1"}, {"created_at": 1555089470.0, "distinguished": null, "type": "comment", "score": 1, "id": "ekqc4in"}, {"created_at": 1555089016.0, "distinguished": null, "type": "comment", "score": 2, "id": "ekqbaf5"}, {"created_at": 1555073208.0, "distinguished": null, "type": "comment", "score": 59, "id": "ekplqoq"}, {"created_at": 1555070987.0, "distinguished": null, "type": "comment", "score": 12, "id": "ekpip38"}, {"created_at": 1555070246.0, "distinguished": null, "type": "comment", "score": 37, "id": "ekphqjg"}, {"created_at": 1555058620.0, "distinguished": null, "type": "comment", "score": 3, "id": "ekp6x91"}, {"created_at": 1555054964.0, "distinguished": null, "type": "comment", "score": 3, "id": "ekp3vyb"}, {"created_at": 1555036110.0, "distinguished": null, "type": "comment", "score": 10, "id": "ekolqjh"}, {"created_at": 1555024756.0, "distinguished": null, "type": "comment", "score": 4, "id": "eko6iyq"}, {"created_at": 1555014394.0, "distinguished": null, "type": "comment", "score": 19, "id": "eknr117"}, {"created_at": 1555013890.0, "distinguished": null, "type": "comment", "score": 58, "id": "eknq840"}, {"created_at": 1555003241.0, "distinguished": null, "type": "comment", "score": 1, "id": "ekn8yfu"}, {"created_at": 1555002917.0, "distinguished": null, "type": "comment", "score": 11, "id": "ekn8fjs"}, {"created_at": 1554974422.0, "distinguished": null, "type": "comment", "score": 42, "id": "ekm754v"}, {"created_at": 1554961533.0, "distinguished": null, "type": "comment", "score": 3, "id": "eklxvhb"}, {"created_at": 1554960767.0, "distinguished": null, "type": "comment", "score": 62, "id": "eklxd1h"}, {"created_at": 1554958383.0, "distinguished": null, "type": "comment", "score": 1, "id": "eklwngp"}, {"created_at": 1554955026.0, "distinguished": null, "type": "comment", "score": 11, "id": "eklt2hr"}, {"created_at": 1554954805.0, "distinguished": null, "type": "comment", "score": 53, "id": "eklstm0"}, {"created_at": 1554951873.0, "distinguished": null, "type": "comment", "score": 5, "id": "eklpf7s"}, {"created_at": 1554950988.0, "distinguished": null, "type": "comment", "score": 6, "id": "eklocbv"}, {"created_at": 1554950617.0, "distinguished": null, "type": "comment", "score": 15, "id": "eklnuqn"}, {"created_at": 1554948703.0, "distinguished": null, "type": "comment", "score": 3, "id": "ekllb1i"}, {"created_at": 1554948373.0, "distinguished": null, "type": "comment", "score": 14, "id": "eklkvah"}, {"created_at": 1554940570.0, "distinguished": null, "type": "comment", "score": 1, "id": "ekla1y6"}, {"created_at": 1554940328.0, "distinguished": null, "type": "comment", "score": 6, "id": "ekl9px4"}, {"created_at": 1554936991.0, "distinguished": null, "type": "submission", "score": 36, "id": "bbsnu6"}, {"created_at": 1554936671.0, "distinguished": null, "type": "comment", "score": 1, "id": "ekl47ep"}, {"created_at": 1554923791.0, "distinguished": null, "type": "comment", "score": 2, "id": "ekkj7wz"}, {"created_at": 1554860754.0, "distinguished": null, "type": "comment", "score": 3, "id": "ekimvto"}, {"created_at": 1554859873.0, "distinguished": null, "type": "comment", "score": 1, "id": "ekilppz"}, {"created_at": 1554859810.0, "distinguished": null, "type": "comment", "score": 0, "id": "ekilmik"}, {"created_at": 1554859284.0, "distinguished": null, "type": "comment", "score": 1, "id": "ekikwv4"}, {"created_at": 1554858928.0, "distinguished": null, "type": "comment", "score": 9, "id": "ekikfjo"}, {"created_at": 1554858814.0, "distinguished": null, "type": "comment", "score": 9, "id": "ekik9ud"}, {"created_at": 1554858227.0, "distinguished": null, "type": "comment", "score": 3, "id": "ekijgle"}, {"created_at": 1554858168.0, "distinguished": null, "type": "comment", "score": 4, "id": "ekijdmy"}, {"created_at": 1554858025.0, "distinguished": null, "type": "comment", "score": 6, "id": "ekij6m8"}, {"created_at": 1554857784.0, "distinguished": null, "type": "comment", "score": 2, "id": "ekiiuc2"}, {"created_at": 1554857624.0, "distinguished": null, "type": "comment", "score": 3, "id": "ekiim64"}, {"created_at": 1554857533.0, "distinguished": null, "type": "comment", "score": 2, "id": "ekiihn0"}, {"created_at": 1554857133.0, "distinguished": null, "type": "comment", "score": 6, "id": "ekihx28"}, {"created_at": 1554856923.0, "distinguished": null, "type": "comment", "score": 1, "id": "ekihm3c"}, {"created_at": 1554856667.0, "distinguished": null, "type": "comment", "score": 2, "id": "ekih8wb"}, {"created_at": 1554856586.0, "distinguished": null, "type": "comment", "score": 13, "id": "ekih4yi"}, {"created_at": 1554856437.0, "distinguished": null, "type": "comment", "score": 2, "id": "ekigxrf"}, {"created_at": 1554856156.0, "distinguished": null, "type": "comment", "score": 1, "id": "ekigk9f"}, {"created_at": 1554855585.0, "distinguished": null, "type": "comment", "score": 6, "id": "ekiftbx"}, {"created_at": 1554855411.0, "distinguished": null, "type": "comment", "score": 8, "id": "ekifl3g"}, {"created_at": 1554855239.0, "distinguished": null, "type": "comment", "score": 7, "id": "ekifcmj"}, {"created_at": 1554855028.0, "distinguished": null, "type": "comment", "score": 3, "id": "ekif2pe"}, {"created_at": 1554854569.0, "distinguished": null, "type": "comment", "score": 2, "id": "ekiehc5"}, {"created_at": 1554850774.0, "distinguished": null, "type": "comment", "score": 4, "id": "eki9hff"}, {"created_at": 1554850721.0, "distinguished": null, "type": "comment", "score": 3, "id": "eki9ezc"}, {"created_at": 1554823222.0, "distinguished": null, "type": "comment", "score": 1, "id": "ekh3bv6"}, {"created_at": 1554798034.0, "distinguished": null, "type": "comment", "score": 2, "id": "ekgf1t8"}, {"created_at": 1554795292.0, "distinguished": null, "type": "comment", "score": 46, "id": "ekgdimm"}, {"created_at": 1554788520.0, "distinguished": null, "type": "comment", "score": 2, "id": "ekg908v"}, {"created_at": 1554786522.0, "distinguished": null, "type": "comment", "score": 8, "id": "ekg7e7b"}, {"created_at": 1554744051.0, "distinguished": null, "type": "comment", "score": 1, "id": "ekeg8go"}, {"created_at": 1554744020.0, "distinguished": null, "type": "comment", "score": 1, "id": "ekeg6qf"}, {"created_at": 1554699375.0, "distinguished": null, "type": "comment", "score": 8, "id": "ekda10e"}, {"created_at": 1554693072.0, "distinguished": null, "type": "comment", "score": 15, "id": "ekd3d3f"}, {"created_at": 1554690515.0, "distinguished": null, "type": "comment", "score": 3, "id": "ekd08qp"}, {"created_at": 1554688473.0, "distinguished": null, "type": "comment", "score": 3, "id": "ekcxq2i"}, {"created_at": 1554683304.0, "distinguished": null, "type": "comment", "score": 5, "id": "ekcr9ar"}, {"created_at": 1554663907.0, "distinguished": null, "type": "comment", "score": 1, "id": "ekbz2hw"}, {"created_at": 1554663205.0, "distinguished": null, "type": "comment", "score": -1, "id": "ekby16q"}, {"created_at": 1554663144.0, "distinguished": null, "type": "comment", "score": 1, "id": "ekbxy2x"}, {"created_at": 1554661134.0, "distinguished": null, "type": "comment", "score": 2, "id": "ekbv5s6"}, {"created_at": 1554629640.0, "distinguished": null, "type": "comment", "score": 1, "id": "ekayt5c"}, {"created_at": 1554629260.0, "distinguished": null, "type": "comment", "score": 5, "id": "ekaylzd"}, {"created_at": 1554613885.0, "distinguished": null, "type": "comment", "score": 14, "id": "ekap616"}, {"created_at": 1554584143.0, "distinguished": null, "type": "comment", "score": 6, "id": "ek9s20i"}, {"created_at": 1554582283.0, "distinguished": null, "type": "comment", "score": 13, "id": "ek9pvk5"}, {"created_at": 1554514633.0, "distinguished": null, "type": "comment", "score": 1, "id": "ek7ytld"}, {"created_at": 1554514243.0, "distinguished": null, "type": "comment", "score": 3, "id": "ek7yd69"}, {"created_at": 1554514139.0, "distinguished": null, "type": "comment", "score": 1, "id": "ek7y8xo"}, {"created_at": 1554513967.0, "distinguished": null, "type": "comment", "score": 2, "id": "ek7y1lv"}, {"created_at": 1554513682.0, "distinguished": null, "type": "comment", "score": 1, "id": "ek7xprb"}, {"created_at": 1554513624.0, "distinguished": null, "type": "comment", "score": 1, "id": "ek7xnae"}, {"created_at": 1554513340.0, "distinguished": null, "type": "comment", "score": 2, "id": "ek7xbj5"}, {"created_at": 1554513091.0, "distinguished": null, "type": "comment", "score": 2, "id": "ek7x13m"}, {"created_at": 1554512275.0, "distinguished": null, "type": "comment", "score": 1, "id": "ek7w39n"}, {"created_at": 1554512193.0, "distinguished": null, "type": "comment", "score": 4, "id": "ek7vztx"}, {"created_at": 1554512142.0, "distinguished": null, "type": "comment", "score": 1, "id": "ek7vxog"}, {"created_at": 1554512087.0, "distinguished": null, "type": "comment", "score": 3, "id": "ek7vveg"}, {"created_at": 1554511695.0, "distinguished": null, "type": "comment", "score": 1, "id": "ek7vf80"}, {"created_at": 1554511611.0, "distinguished": null, "type": "comment", "score": 1, "id": "ek7vbgk"}, {"created_at": 1554511326.0, "distinguished": null, "type": "comment", "score": 3, "id": "ek7uz32"}, {"created_at": 1554511270.0, "distinguished": null, "type": "comment", "score": 20, "id": "ek7uwnb"}, {"created_at": 1554445020.0, "distinguished": null, "type": "comment", "score": 1, "id": "ek5rgl8"}, {"created_at": 1554444527.0, "distinguished": null, "type": "comment", "score": 3, "id": "ek5r399"}, {"created_at": 1554420925.0, "distinguished": null, "type": "comment", "score": 7, "id": "ek51dlh"}, {"created_at": 1554404823.0, "distinguished": null, "type": "comment", "score": 1, "id": "ek4eunh"}, {"created_at": 1554404545.0, "distinguished": null, "type": "comment", "score": 23, "id": "ek4efb6"}, {"created_at": 1554391927.0, "distinguished": null, "type": "comment", "score": 11, "id": "ek3v9v6"}, {"created_at": 1554341297.0, "distinguished": null, "type": "comment", "score": -7, "id": "ek2ju1k"}, {"created_at": 1554339800.0, "distinguished": null, "type": "comment", "score": 3, "id": "ek2hxkj"}, {"created_at": 1554339025.0, "distinguished": null, "type": "comment", "score": 4, "id": "ek2gy7m"}, {"created_at": 1554338780.0, "distinguished": null, "type": "comment", "score": 3, "id": "ek2gn2o"}, {"created_at": 1554336564.0, "distinguished": null, "type": "comment", "score": 3, "id": "ek2dt4t"}, {"created_at": 1554336030.0, "distinguished": null, "type": "comment", "score": 3, "id": "ek2d4h3"}, {"created_at": 1554335371.0, "distinguished": null, "type": "comment", "score": 5, "id": "ek2c9zu"}, {"created_at": 1554335225.0, "distinguished": null, "type": "comment", "score": 2, "id": "ek2c3bz"}, {"created_at": 1554334862.0, "distinguished": null, "type": "comment", "score": 2, "id": "ek2bm9d"}, {"created_at": 1554334152.0, "distinguished": null, "type": "submission", "score": 4, "id": "b95bqt"}, {"created_at": 1554332827.0, "distinguished": null, "type": "comment", "score": 10, "id": "ek28y1n"}, {"created_at": 1554330643.0, "distinguished": null, "type": "comment", "score": 4, "id": "ek260yz"}, {"created_at": 1554238548.0, "distinguished": null, "type": "comment", "score": 22, "id": "ejz5bku"}, {"created_at": 1554229596.0, "distinguished": null, "type": "comment", "score": 6, "id": "ejyr9qb"}, {"created_at": 1554174417.0, "distinguished": null, "type": "comment", "score": 14, "id": "ejx99xw"}, {"created_at": 1554169393.0, "distinguished": null, "type": "comment", "score": 4, "id": "ejx31f7"}, {"created_at": 1554167045.0, "distinguished": null, "type": "comment", "score": 3, "id": "ejx00tj"}, {"created_at": 1554166354.0, "distinguished": null, "type": "comment", "score": 2, "id": "ejwz5jr"}, {"created_at": 1554164640.0, "distinguished": null, "type": "comment", "score": 3, "id": "ejwwy7c"}, {"created_at": 1554162765.0, "distinguished": null, "type": "comment", "score": 3, "id": "ejwuirk"}, {"created_at": 1554157495.0, "distinguished": null, "type": "comment", "score": 7, "id": "ejwnoed"}, {"created_at": 1554140648.0, "distinguished": null, "type": "comment", "score": 329, "id": "ejvzhfq"}, {"created_at": 1554096604.0, "distinguished": null, "type": "submission", "score": 72, "id": "b7xwpw"}, {"created_at": 1554077323.0, "distinguished": null, "type": "comment", "score": 1, "id": "ejub843"}, {"created_at": 1554059363.0, "distinguished": null, "type": "comment", "score": 8, "id": "ejto5hn"}, {"created_at": 1554053978.0, "distinguished": null, "type": "comment", "score": 44, "id": "ejtg49q"}, {"created_at": 1554005547.0, "distinguished": null, "type": "comment", "score": 50, "id": "ejs9q1m"}, {"created_at": 1553997726.0, "distinguished": null, "type": "comment", "score": 10, "id": "ejs1dod"}, {"created_at": 1553997628.0, "distinguished": null, "type": "comment", "score": 4, "id": "ejs19k6"}, {"created_at": 1553997346.0, "distinguished": null, "type": "comment", "score": 1, "id": "ejs0x1y"}, {"created_at": 1553997278.0, "distinguished": null, "type": "comment", "score": 4, "id": "ejs0u41"}, {"created_at": 1553997103.0, "distinguished": null, "type": "comment", "score": 2, "id": "ejs0mqe"}, {"created_at": 1553996955.0, "distinguished": null, "type": "comment", "score": 5, "id": "ejs0ggk"}, {"created_at": 1553996858.0, "distinguished": null, "type": "comment", "score": 13, "id": "ejs0cd3"}, {"created_at": 1553994463.0, "distinguished": null, "type": "comment", "score": 1, "id": "ejrxghv"}, {"created_at": 1553994357.0, "distinguished": null, "type": "comment", "score": 1, "id": "ejrxc0s"}, {"created_at": 1553994334.0, "distinguished": null, "type": "comment", "score": 5, "id": "ejrxb2z"}, {"created_at": 1553994275.0, "distinguished": null, "type": "comment", "score": 6, "id": "ejrx8l6"}, {"created_at": 1553994008.0, "distinguished": null, "type": "comment", "score": 3, "id": "ejrwxir"}, {"created_at": 1553993650.0, "distinguished": null, "type": "comment", "score": 9, "id": "ejrwinx"}, {"created_at": 1553992142.0, "distinguished": null, "type": "comment", "score": 9, "id": "ejrurfx"}, {"created_at": 1553990796.0, "distinguished": null, "type": "comment", "score": 3, "id": "ejrt4xc"}, {"created_at": 1553980599.0, "distinguished": null, "type": "comment", "score": 6, "id": "ejrfhs0"}, {"created_at": 1553975419.0, "distinguished": null, "type": "comment", "score": 23, "id": "ejr8iu3"}, {"created_at": 1553830447.0, "distinguished": null, "type": "comment", "score": 4, "id": "ejmso1p"}, {"created_at": 1553824726.0, "distinguished": null, "type": "comment", "score": 5, "id": "ejmljpj"}, {"created_at": 1553784095.0, "distinguished": null, "type": "comment", "score": 0, "id": "ejks1l7"}, {"created_at": 1553783878.0, "distinguished": null, "type": "comment", "score": 30, "id": "ejkrp7d"}, {"created_at": 1553737806.0, "distinguished": null, "type": "comment", "score": 8, "id": "ejjjv3k"}, {"created_at": 1553651029.0, "distinguished": null, "type": "comment", "score": 1, "id": "ejgrh9y"}, {"created_at": 1553650990.0, "distinguished": null, "type": "comment", "score": 1, "id": "ejgrfd3"}, {"created_at": 1553650586.0, "distinguished": null, "type": "comment", "score": 1, "id": "ejgqvic"}, {"created_at": 1553650468.0, "distinguished": null, "type": "comment", "score": 6, "id": "ejgqpp9"}, {"created_at": 1553649447.0, "distinguished": null, "type": "comment", "score": 3, "id": "ejgpb9u"}, {"created_at": 1553649006.0, "distinguished": null, "type": "comment", "score": 7, "id": "ejgoq0e"}, {"created_at": 1553648685.0, "distinguished": null, "type": "comment", "score": 4, "id": "ejgoaey"}, {"created_at": 1553648485.0, "distinguished": null, "type": "comment", "score": 1, "id": "ejgo0v8"}, {"created_at": 1553647932.0, "distinguished": null, "type": "comment", "score": 6, "id": "ejgn9n4"}, {"created_at": 1553647715.0, "distinguished": null, "type": "comment", "score": 7, "id": "ejgmyv6"}, {"created_at": 1553646803.0, "distinguished": null, "type": "comment", "score": 4, "id": "ejglq31"}, {"created_at": 1553646567.0, "distinguished": null, "type": "comment", "score": 1, "id": "ejgletl"}, {"created_at": 1553639134.0, "distinguished": null, "type": "comment", "score": 4, "id": "ejgbbtf"}, {"created_at": 1553616106.0, "distinguished": null, "type": "comment", "score": 2, "id": "ejfbqi6"}, {"created_at": 1553577000.0, "distinguished": null, "type": "comment", "score": 8, "id": "ejebevt"}, {"created_at": 1553550661.0, "distinguished": null, "type": "comment", "score": 4, "id": "ejddpv4"}, {"created_at": 1553550600.0, "distinguished": null, "type": "comment", "score": 14, "id": "ejddmm8"}, {"created_at": 1553481296.0, "distinguished": null, "type": "comment", "score": 3, "id": "ejb95ra"}, {"created_at": 1553474939.0, "distinguished": null, "type": "comment", "score": 5, "id": "ejb16hy"}, {"created_at": 1553473970.0, "distinguished": null, "type": "comment", "score": 1, "id": "ejazxu9"}, {"created_at": 1553473659.0, "distinguished": null, "type": "comment", "score": -1, "id": "ejaziy0"}, {"created_at": 1553473563.0, "distinguished": null, "type": "comment", "score": 2, "id": "ejaze46"}, {"created_at": 1553473443.0, "distinguished": null, "type": "comment", "score": 3, "id": "ejaz86b"}, {"created_at": 1553473078.0, "distinguished": null, "type": "comment", "score": 2, "id": "ejayrb3"}, {"created_at": 1553472589.0, "distinguished": null, "type": "comment", "score": 3, "id": "ejay4ma"}, {"created_at": 1553471838.0, "distinguished": null, "type": "comment", "score": 4, "id": "ejax5bo"}, {"created_at": 1553471412.0, "distinguished": null, "type": "comment", "score": 2, "id": "ejawkxa"}, {"created_at": 1553471065.0, "distinguished": null, "type": "comment", "score": 2, "id": "ejaw3n8"}, {"created_at": 1553470839.0, "distinguished": null, "type": "comment", "score": -1, "id": "ejavsn7"}, {"created_at": 1553470762.0, "distinguished": null, "type": "comment", "score": 3, "id": "ejavot5"}, {"created_at": 1553470651.0, "distinguished": null, "type": "comment", "score": 1, "id": "ejavj9e"}, {"created_at": 1553470440.0, "distinguished": null, "type": "comment", "score": 4, "id": "ejav8ej"}, {"created_at": 1553469457.0, "distinguished": null, "type": "comment", "score": 4, "id": "ejatw6q"}, {"created_at": 1553468764.0, "distinguished": null, "type": "comment", "score": 6, "id": "ejasyio"}, {"created_at": 1553468649.0, "distinguished": null, "type": "comment", "score": 3, "id": "ejast2z"}, {"created_at": 1553468267.0, "distinguished": null, "type": "comment", "score": 2, "id": "ejasajx"}, {"created_at": 1553468151.0, "distinguished": null, "type": "comment", "score": 2, "id": "ejas4y0"}, {"created_at": 1553468006.0, "distinguished": null, "type": "comment", "score": 3, "id": "ejarxvo"}, {"created_at": 1553467923.0, "distinguished": null, "type": "comment", "score": 1, "id": "ejartv3"}, {"created_at": 1553467767.0, "distinguished": null, "type": "comment", "score": 2, "id": "ejarmap"}, {"created_at": 1553467350.0, "distinguished": null, "type": "comment", "score": 8, "id": "ejar1p3"}, {"created_at": 1553467029.0, "distinguished": null, "type": "comment", "score": 4, "id": "ejaqlk2"}, {"created_at": 1553466933.0, "distinguished": null, "type": "comment", "score": 1, "id": "ejaqgxz"}, {"created_at": 1553466247.0, "distinguished": null, "type": "comment", "score": 3, "id": "ejapjil"}, {"created_at": 1553466059.0, "distinguished": null, "type": "comment", "score": 7, "id": "ejapac1"}, {"created_at": 1553465949.0, "distinguished": null, "type": "comment", "score": 1, "id": "ejap4us"}, {"created_at": 1553465875.0, "distinguished": null, "type": "comment", "score": 2, "id": "ejap143"}, {"created_at": 1553465809.0, "distinguished": null, "type": "comment", "score": 1, "id": "ejaoxry"}, {"created_at": 1553465667.0, "distinguished": null, "type": "comment", "score": 2, "id": "ejaoqsj"}, {"created_at": 1553465635.0, "distinguished": null, "type": "comment", "score": 1, "id": "ejaop6u"}, {"created_at": 1553464173.0, "distinguished": null, "type": "comment", "score": 1, "id": "ejamna7"}, {"created_at": 1553463180.0, "distinguished": null, "type": "comment", "score": 6, "id": "ejal8ip"}, {"created_at": 1553462626.0, "distinguished": null, "type": "comment", "score": 1, "id": "ejakghn"}, {"created_at": 1553462000.0, "distinguished": null, "type": "comment", "score": 1, "id": "ejajl1z"}, {"created_at": 1553457143.0, "distinguished": null, "type": "comment", "score": 65, "id": "ejacpbu"}, {"created_at": 1553364600.0, "distinguished": null, "type": "comment", "score": 1, "id": "ej7l3in"}, {"created_at": 1553332286.0, "distinguished": null, "type": "comment", "score": 2, "id": "ej6m7ww"}, {"created_at": 1553312175.0, "distinguished": null, "type": "comment", "score": 1, "id": "ej670q2"}, {"created_at": 1553311835.0, "distinguished": null, "type": "comment", "score": 15, "id": "ej66nxy"}, {"created_at": 1553306091.0, "distinguished": null, "type": "comment", "score": 1, "id": "ej602gp"}, {"created_at": 1553305125.0, "distinguished": null, "type": "comment", "score": 1, "id": "ej5yweo"}, {"created_at": 1553296145.0, "distinguished": null, "type": "comment", "score": 6, "id": "ej5nqu3"}, {"created_at": 1553276962.0, "distinguished": null, "type": "comment", "score": 15, "id": "ej4uljs"}, {"created_at": 1553210424.0, "distinguished": null, "type": "comment", "score": 1, "id": "ej2utpe"}, {"created_at": 1553210138.0, "distinguished": null, "type": "comment", "score": 1, "id": "ej2uge5"}, {"created_at": 1553207061.0, "distinguished": null, "type": "comment", "score": 23, "id": "ej2qboe"}, {"created_at": 1553186695.0, "distinguished": null, "type": "comment", "score": 45, "id": "ej1ubxs"}, {"created_at": 1553177112.0, "distinguished": null, "type": "comment", "score": 4, "id": "ej1ejyp"}, {"created_at": 1553142620.0, "distinguished": null, "type": "comment", "score": 13, "id": "ej0l7e9"}, {"created_at": 1553142385.0, "distinguished": null, "type": "comment", "score": 5, "id": "ej0kyp4"}, {"created_at": 1553142342.0, "distinguished": null, "type": "comment", "score": 1, "id": "ej0kx25"}, {"created_at": 1553142092.0, "distinguished": null, "type": "comment", "score": 8, "id": "ej0knle"}, {"created_at": 1553141925.0, "distinguished": null, "type": "comment", "score": 3, "id": "ej0kh79"}, {"created_at": 1553141873.0, "distinguished": null, "type": "comment", "score": 8, "id": "ej0kf8c"}, {"created_at": 1553141723.0, "distinguished": null, "type": "comment", "score": 1, "id": "ej0k9mx"}, {"created_at": 1553141541.0, "distinguished": null, "type": "comment", "score": 2, "id": "ej0k2rd"}, {"created_at": 1553141319.0, "distinguished": null, "type": "comment", "score": 3, "id": "ej0ju9l"}, {"created_at": 1553141212.0, "distinguished": null, "type": "comment", "score": 2, "id": "ej0jq2s"}, {"created_at": 1553141017.0, "distinguished": null, "type": "comment", "score": 2, "id": "ej0jidj"}, {"created_at": 1553140981.0, "distinguished": null, "type": "comment", "score": 2, "id": "ej0jh07"}, {"created_at": 1553140882.0, "distinguished": null, "type": "comment", "score": 2, "id": "ej0jd8j"}, {"created_at": 1553140825.0, "distinguished": null, "type": "comment", "score": 5, "id": "ej0jb14"}, {"created_at": 1553140679.0, "distinguished": null, "type": "comment", "score": 2, "id": "ej0j5cl"}, {"created_at": 1553140400.0, "distinguished": null, "type": "comment", "score": 10, "id": "ej0iug7"}, {"created_at": 1553140269.0, "distinguished": null, "type": "comment", "score": 1, "id": "ej0ip8c"}, {"created_at": 1553140043.0, "distinguished": null, "type": "comment", "score": 4, "id": "ej0ig94"}, {"created_at": 1553139906.0, "distinguished": null, "type": "comment", "score": 9, "id": "ej0iau1"}, {"created_at": 1553139811.0, "distinguished": null, "type": "comment", "score": 7, "id": "ej0i71e"}, {"created_at": 1553139728.0, "distinguished": null, "type": "comment", "score": 3, "id": "ej0i3rx"}, {"created_at": 1553139539.0, "distinguished": null, "type": "comment", "score": 4, "id": "ej0hw6p"}, {"created_at": 1553139346.0, "distinguished": null, "type": "comment", "score": 2, "id": "ej0hobw"}, {"created_at": 1553138933.0, "distinguished": null, "type": "comment", "score": 2, "id": "ej0h7l4"}, {"created_at": 1553138691.0, "distinguished": null, "type": "comment", "score": 10, "id": "ej0gxe9"}, {"created_at": 1553138573.0, "distinguished": null, "type": "comment", "score": 2, "id": "ej0gsdu"}, {"created_at": 1553138408.0, "distinguished": null, "type": "comment", "score": 4, "id": "ej0glfk"}, {"created_at": 1553138227.0, "distinguished": null, "type": "comment", "score": 2, "id": "ej0gdkl"}, {"created_at": 1553137944.0, "distinguished": null, "type": "comment", "score": 7, "id": "ej0g1px"}, {"created_at": 1553137744.0, "distinguished": null, "type": "comment", "score": 3, "id": "ej0ftb3"}, {"created_at": 1553137601.0, "distinguished": null, "type": "comment", "score": 5, "id": "ej0fn8y"}, {"created_at": 1553137457.0, "distinguished": null, "type": "comment", "score": 5, "id": "ej0fh4x"}, {"created_at": 1553137371.0, "distinguished": null, "type": "comment", "score": 3, "id": "ej0fde0"}, {"created_at": 1553137320.0, "distinguished": null, "type": "comment", "score": 4, "id": "ej0fb6q"}, {"created_at": 1553136250.0, "distinguished": null, "type": "comment", "score": 5, "id": "ej0dzq9"}, {"created_at": 1553136002.0, "distinguished": null, "type": "comment", "score": 7, "id": "ej0doei"}, {"created_at": 1553135869.0, "distinguished": null, "type": "comment", "score": 1, "id": "ej0dibj"}, {"created_at": 1553135731.0, "distinguished": null, "type": "comment", "score": 3, "id": "ej0dc3k"}, {"created_at": 1553135692.0, "distinguished": null, "type": "comment", "score": 5, "id": "ej0dacg"}, {"created_at": 1553135445.0, "distinguished": null, "type": "comment", "score": 5, "id": "ej0cz30"}, {"created_at": 1553135409.0, "distinguished": null, "type": "comment", "score": 3, "id": "ej0cxcr"}, {"created_at": 1553135044.0, "distinguished": null, "type": "comment", "score": 4, "id": "ej0cgf1"}, {"created_at": 1553134936.0, "distinguished": null, "type": "comment", "score": 5, "id": "ej0cbds"}, {"created_at": 1553134738.0, "distinguished": null, "type": "comment", "score": 2, "id": "ej0c225"}, {"created_at": 1553134675.0, "distinguished": null, "type": "comment", "score": 2, "id": "ej0bz3d"}, {"created_at": 1553134459.0, "distinguished": null, "type": "comment", "score": 1, "id": "ej0bp60"}, {"created_at": 1553134295.0, "distinguished": null, "type": "comment", "score": 1, "id": "ej0bhh7"}, {"created_at": 1553134186.0, "distinguished": null, "type": "comment", "score": 2, "id": "ej0bcbl"}, {"created_at": 1553134146.0, "distinguished": null, "type": "comment", "score": 2, "id": "ej0bad8"}, {"created_at": 1553134036.0, "distinguished": null, "type": "comment", "score": 1, "id": "ej0b5bw"}, {"created_at": 1553133896.0, "distinguished": null, "type": "comment", "score": 1, "id": "ej0ayxx"}, {"created_at": 1553133786.0, "distinguished": null, "type": "comment", "score": 6, "id": "ej0atms"}, {"created_at": 1553133686.0, "distinguished": null, "type": "comment", "score": 3, "id": "ej0aov2"}, {"created_at": 1553133468.0, "distinguished": null, "type": "comment", "score": 5, "id": "ej0aefr"}, {"created_at": 1553133388.0, "distinguished": null, "type": "comment", "score": 2, "id": "ej0aaoo"}, {"created_at": 1553133282.0, "distinguished": null, "type": "comment", "score": 1, "id": "ej0a5os"}, {"created_at": 1553133230.0, "distinguished": null, "type": "comment", "score": 1, "id": "ej0a37f"}, {"created_at": 1553133142.0, "distinguished": null, "type": "comment", "score": 2, "id": "ej09z18"}, {"created_at": 1553133080.0, "distinguished": null, "type": "comment", "score": 3, "id": "ej09w1c"}, {"created_at": 1553133022.0, "distinguished": null, "type": "comment", "score": 3, "id": "ej09t9z"}, {"created_at": 1553132951.0, "distinguished": null, "type": "comment", "score": 5, "id": "ej09pt9"}, {"created_at": 1553132907.0, "distinguished": null, "type": "comment", "score": 2, "id": "ej09npd"}, {"created_at": 1553132844.0, "distinguished": null, "type": "comment", "score": 1, "id": "ej09kny"}, {"created_at": 1553132761.0, "distinguished": null, "type": "comment", "score": 1, "id": "ej09gf9"}, {"created_at": 1553132664.0, "distinguished": null, "type": "comment", "score": 3, "id": "ej09bjl"}, {"created_at": 1553131489.0, "distinguished": null, "type": "comment", "score": 1, "id": "ej07q6w"}, {"created_at": 1553131380.0, "distinguished": null, "type": "comment", "score": 9, "id": "ej07kyh"}, {"created_at": 1553128148.0, "distinguished": null, "type": "comment", "score": 1, "id": "ej0380u"}, {"created_at": 1553115078.0, "distinguished": null, "type": "comment", "score": 9, "id": "eizjxgb"}, {"created_at": 1553077018.0, "distinguished": null, "type": "comment", "score": 14, "id": "eiy4btg"}, {"created_at": 1553017806.0, "distinguished": null, "type": "comment", "score": 26, "id": "eiw80lk"}, {"created_at": 1553016862.0, "distinguished": null, "type": "submission", "score": 224, "id": "b30b9c"}, {"created_at": 1553010050.0, "distinguished": null, "type": "comment", "score": 10, "id": "eivvr5n"}, {"created_at": 1552960795.0, "distinguished": null, "type": "comment", "score": 27, "id": "eiujh8x"}, {"created_at": 1552960687.0, "distinguished": null, "type": "comment", "score": 4, "id": "eiujc64"}, {"created_at": 1552959398.0, "distinguished": null, "type": "comment", "score": 18, "id": "eiuhohx"}, {"created_at": 1552959092.0, "distinguished": null, "type": "comment", "score": 4, "id": "eiuhadd"}, {"created_at": 1552958826.0, "distinguished": null, "type": "comment", "score": 1, "id": "eiugxxb"}, {"created_at": 1552931065.0, "distinguished": null, "type": "comment", "score": 7, "id": "eiteu0u"}, {"created_at": 1552924865.0, "distinguished": null, "type": "comment", "score": 3, "id": "eit5m15"}, {"created_at": 1552923603.0, "distinguished": null, "type": "comment", "score": 8, "id": "eit3si9"}, {"created_at": 1552922508.0, "distinguished": null, "type": "submission", "score": 108, "id": "b2jyzm"}, {"created_at": 1552921890.0, "distinguished": null, "type": "comment", "score": 10, "id": "eit1e7a"}, {"created_at": 1552891772.0, "distinguished": null, "type": "comment", "score": 8, "id": "eisclf3"}, {"created_at": 1552861851.0, "distinguished": null, "type": "comment", "score": 1, "id": "eirgv00"}, {"created_at": 1552861562.0, "distinguished": null, "type": "comment", "score": 14, "id": "eirggqs"}, {"created_at": 1552861252.0, "distinguished": null, "type": "comment", "score": 2, "id": "eirg20v"}, {"created_at": 1552858650.0, "distinguished": null, "type": "comment", "score": 3, "id": "eircglx"}, {"created_at": 1552857288.0, "distinguished": null, "type": "comment", "score": 5, "id": "eirajgf"}, {"created_at": 1552855258.0, "distinguished": null, "type": "comment", "score": 3, "id": "eir7q6s"}, {"created_at": 1552855223.0, "distinguished": null, "type": "comment", "score": 1, "id": "eir7ogc"}, {"created_at": 1552855057.0, "distinguished": null, "type": "comment", "score": 8, "id": "eir7fvo"}, {"created_at": 1552854623.0, "distinguished": null, "type": "comment", "score": 4, "id": "eir6u0q"}, {"created_at": 1552854506.0, "distinguished": null, "type": "comment", "score": 6, "id": "eir6o4t"}, {"created_at": 1552853992.0, "distinguished": null, "type": "comment", "score": 3, "id": "eir5yaw"}, {"created_at": 1552844819.0, "distinguished": null, "type": "comment", "score": 10, "id": "eiqtbm5"}, {"created_at": 1552668453.0, "distinguished": null, "type": "comment", "score": 29, "id": "eill33i"}, {"created_at": 1552667604.0, "distinguished": null, "type": "submission", "score": 107, "id": "b1h0jh"}, {"created_at": 1552586750.0, "distinguished": null, "type": "comment", "score": 20, "id": "eiizivc"}, {"created_at": 1552580716.0, "distinguished": null, "type": "comment", "score": 1, "id": "eiiq0n8"}, {"created_at": 1552578915.0, "distinguished": null, "type": "comment", "score": 1, "id": "eiin76a"}, {"created_at": 1552392228.0, "distinguished": null, "type": "comment", "score": 6, "id": "eicgeco"}, {"created_at": 1552376675.0, "distinguished": null, "type": "comment", "score": 3, "id": "eic6k6t"}, {"created_at": 1552100787.0, "distinguished": null, "type": "comment", "score": 4, "id": "ei47o9j"}, {"created_at": 1552018783.0, "distinguished": null, "type": "comment", "score": 7, "id": "ei1r5v5"}, {"created_at": 1551986454.0, "distinguished": null, "type": "comment", "score": 14, "id": "ei0jwy1"}, {"created_at": 1551920649.0, "distinguished": null, "type": "comment", "score": -6, "id": "ehylpxz"}, {"created_at": 1551919941.0, "distinguished": null, "type": "comment", "score": 6, "id": "ehyktwu"}, {"created_at": 1551919150.0, "distinguished": null, "type": "submission", "score": 67, "id": "ay6bzu"}, {"created_at": 1551913036.0, "distinguished": null, "type": "comment", "score": 11, "id": "ehybkhc"}, {"created_at": 1551910962.0, "distinguished": null, "type": "comment", "score": 5, "id": "ehy8fba"}, {"created_at": 1551844429.0, "distinguished": null, "type": "comment", "score": 18, "id": "ehw6wwe"}, {"created_at": 1551843122.0, "distinguished": null, "type": "comment", "score": 6, "id": "ehw5arz"}, {"created_at": 1551843083.0, "distinguished": null, "type": "comment", "score": 4, "id": "ehw5909"}, {"created_at": 1551842888.0, "distinguished": null, "type": "comment", "score": 2, "id": "ehw502q"}, {"created_at": 1551841531.0, "distinguished": null, "type": "comment", "score": 8, "id": "ehw3abf"}, {"created_at": 1551840272.0, "distinguished": null, "type": "comment", "score": 1, "id": "ehw1myn"}, {"created_at": 1551839862.0, "distinguished": null, "type": "comment", "score": 3, "id": "ehw13ll"}, {"created_at": 1551839781.0, "distinguished": null, "type": "comment", "score": 2, "id": "ehw0ztf"}, {"created_at": 1551839650.0, "distinguished": null, "type": "comment", "score": 2, "id": "ehw0tlp"}, {"created_at": 1551837377.0, "distinguished": null, "type": "comment", "score": 1, "id": "ehvxtqi"}, {"created_at": 1551837310.0, "distinguished": null, "type": "comment", "score": 2, "id": "ehvxqis"}, {"created_at": 1551837205.0, "distinguished": null, "type": "comment", "score": 2, "id": "ehvxlj7"}, {"created_at": 1551837104.0, "distinguished": null, "type": "comment", "score": 1, "id": "ehvxgvi"}, {"created_at": 1551836925.0, "distinguished": null, "type": "comment", "score": 4, "id": "ehvx8mj"}, {"created_at": 1551836809.0, "distinguished": null, "type": "comment", "score": 10, "id": "ehvx2zb"}, {"created_at": 1551770977.0, "distinguished": null, "type": "comment", "score": 3, "id": "ehtrwlr"}, {"created_at": 1551766094.0, "distinguished": null, "type": "comment", "score": 5, "id": "ehto9r0"}, {"created_at": 1551753525.0, "distinguished": null, "type": "comment", "score": 3, "id": "ehtbk2v"}, {"created_at": 1551747366.0, "distinguished": null, "type": "comment", "score": 3, "id": "eht3n5c"}, {"created_at": 1551720447.0, "distinguished": null, "type": "comment", "score": 63, "id": "ehs1n1k"}, {"created_at": 1551659321.0, "distinguished": null, "type": "comment", "score": 4, "id": "ehqgjm2"}, {"created_at": 1551657112.0, "distinguished": null, "type": "comment", "score": 6, "id": "ehqdw6o"}, {"created_at": 1551655832.0, "distinguished": null, "type": "comment", "score": 8, "id": "ehqcbdo"}, {"created_at": 1551655556.0, "distinguished": null, "type": "comment", "score": 5, "id": "ehqbywb"}, {"created_at": 1551564387.0, "distinguished": null, "type": "comment", "score": 15, "id": "ehnnu3v"}, {"created_at": 1551563971.0, "distinguished": null, "type": "comment", "score": 63, "id": "ehnnasv"}, {"created_at": 1551501437.0, "distinguished": null, "type": "comment", "score": 44, "id": "ehlvkle"}, {"created_at": 1551501077.0, "distinguished": null, "type": "submission", "score": 67, "id": "awdwai"}, {"created_at": 1551499100.0, "distinguished": null, "type": "comment", "score": 17, "id": "ehlt5sw"}, {"created_at": 1551497875.0, "distinguished": null, "type": "comment", "score": 11, "id": "ehlru3f"}, {"created_at": 1551492674.0, "distinguished": null, "type": "comment", "score": 2, "id": "ehllyv4"}, {"created_at": 1551492618.0, "distinguished": null, "type": "comment", "score": 2, "id": "ehllwjy"}, {"created_at": 1551419357.0, "distinguished": null, "type": "comment", "score": 9, "id": "ehjavm2"}, {"created_at": 1551411869.0, "distinguished": null, "type": "comment", "score": 13, "id": "ehj2kix"}, {"created_at": 1551232431.0, "distinguished": null, "type": "comment", "score": 5, "id": "ehd5jm5"}, {"created_at": 1551232081.0, "distinguished": null, "type": "comment", "score": 2, "id": "ehd539h"}, {"created_at": 1551229756.0, "distinguished": null, "type": "comment", "score": 1, "id": "ehd23a4"}, {"created_at": 1551229464.0, "distinguished": null, "type": "comment", "score": 6, "id": "ehd1qdl"}, {"created_at": 1551222899.0, "distinguished": null, "type": "comment", "score": 1, "id": "ehcti4p"}, {"created_at": 1551071496.0, "distinguished": null, "type": "comment", "score": 61, "id": "eh867gb"}, {"created_at": 1550886792.0, "distinguished": null, "type": "submission", "score": 6, "id": "atpu90"}, {"created_at": 1550847839.0, "distinguished": null, "type": "submission", "score": 1, "id": "atilcd"}, {"created_at": 1550840495.0, "distinguished": null, "type": "comment", "score": 1, "id": "eh0ywxa"}, {"created_at": 1550797297.0, "distinguished": null, "type": "comment", "score": 58, "id": "egzw4uz"}, {"created_at": 1550689729.0, "distinguished": null, "type": "comment", "score": 1, "id": "egwb7zx"}, {"created_at": 1550689652.0, "distinguished": null, "type": "comment", "score": 13, "id": "egwb3up"}, {"created_at": 1550507259.0, "distinguished": null, "type": "comment", "score": 69, "id": "egqj8l0"}, {"created_at": 1550159289.0, "distinguished": null, "type": "comment", "score": -18, "id": "eggoeli"}, {"created_at": 1550075061.0, "distinguished": null, "type": "comment", "score": 20, "id": "ege27bu"}, {"created_at": 1550031414.0, "distinguished": null, "type": "comment", "score": 10, "id": "egczti8"}, {"created_at": 1550030268.0, "distinguished": null, "type": "comment", "score": 16, "id": "egcygse"}, {"created_at": 1550000635.0, "distinguished": null, "type": "comment", "score": 2, "id": "egbtaht"}, {"created_at": 1549917154.0, "distinguished": null, "type": "comment", "score": 8, "id": "eg93bxg"}, {"created_at": 1549917008.0, "distinguished": null, "type": "submission", "score": 15, "id": "apkm6e"}, {"created_at": 1549768329.0, "distinguished": null, "type": "comment", "score": 12, "id": "eg4srwz"}, {"created_at": 1549768086.0, "distinguished": null, "type": "comment", "score": 18, "id": "eg4si96"}, {"created_at": 1549767812.0, "distinguished": null, "type": "submission", "score": 67, "id": "ap00cp"}, {"created_at": 1549601917.0, "distinguished": null, "type": "comment", "score": 5, "id": "eg001a2"}, {"created_at": 1549568999.0, "distinguished": null, "type": "comment", "score": 1, "id": "efysv3v"}, {"created_at": 1549567387.0, "distinguished": null, "type": "comment", "score": 1, "id": "efyqba9"}, {"created_at": 1549565930.0, "distinguished": null, "type": "comment", "score": 2, "id": "efyo3ib"}, {"created_at": 1549565826.0, "distinguished": null, "type": "comment", "score": 1, "id": "efynxk8"}, {"created_at": 1549565632.0, "distinguished": null, "type": "comment", "score": 1, "id": "efynmeu"}, {"created_at": 1549565596.0, "distinguished": null, "type": "submission", "score": 1, "id": "ao72rs"}, {"created_at": 1549564952.0, "distinguished": null, "type": "comment", "score": 1, "id": "efymle7"}, {"created_at": 1549564492.0, "distinguished": null, "type": "comment", "score": 8, "id": "efylwog"}, {"created_at": 1549562727.0, "distinguished": null, "type": "comment", "score": -6, "id": "efyj8ev"}, {"created_at": 1549562081.0, "distinguished": null, "type": "comment", "score": 27, "id": "efyi8hd"}, {"created_at": 1549535092.0, "distinguished": null, "type": "comment", "score": 15, "id": "efxopco"}, {"created_at": 1549521571.0, "distinguished": null, "type": "comment", "score": 1, "id": "efxgd2l"}, {"created_at": 1549505909.0, "distinguished": null, "type": "comment", "score": 5, "id": "efwzwhg"}, {"created_at": 1549424568.0, "distinguished": null, "type": "comment", "score": 186, "id": "efuhzyo"}, {"created_at": 1549399340.0, "distinguished": null, "type": "comment", "score": 2, "id": "eftk8s0"}, {"created_at": 1549121851.0, "distinguished": null, "type": "comment", "score": 2, "id": "eflgk4h"}, {"created_at": 1549069242.0, "distinguished": null, "type": "comment", "score": 35, "id": "efk8j4c"}, {"created_at": 1548998398.0, "distinguished": null, "type": "comment", "score": 2, "id": "efhzhig"}, {"created_at": 1548991065.0, "distinguished": null, "type": "comment", "score": 5, "id": "efhrfqv"}, {"created_at": 1548986984.0, "distinguished": null, "type": "comment", "score": 2, "id": "efhmgaf"}, {"created_at": 1548436378.0, "distinguished": null, "type": "comment", "score": 4, "id": "eexysjf"}, {"created_at": 1548424418.0, "distinguished": null, "type": "comment", "score": 2, "id": "eexdgr2"}, {"created_at": 1547733063.0, "distinguished": null, "type": "comment", "score": 6, "id": "ee9sn0k"}, {"created_at": 1541820950.0, "distinguished": null, "type": "comment", "score": 1, "id": "e9egpl2"}], "id": "torontoraptors"}, {"post_data": [{"created_at": 1555480810.0, "distinguished": null, "type": "comment", "score": 4, "id": "el300gd"}, {"created_at": 1555146410.0, "distinguished": null, "type": "comment", "score": 1, "id": "eksb29t"}, {"created_at": 1555145599.0, "distinguished": null, "type": "comment", "score": 1, "id": "eksamd5"}, {"created_at": 1555144806.0, "distinguished": null, "type": "comment", "score": 4, "id": "eksa5bd"}, {"created_at": 1555045794.0, "distinguished": null, "type": "comment", "score": 2, "id": "ekovs0n"}, {"created_at": 1554951488.0, "distinguished": null, "type": "comment", "score": 9, "id": "ekloyib"}, {"created_at": 1554950789.0, "distinguished": null, "type": "comment", "score": 25, "id": "eklo31x"}, {"created_at": 1554851269.0, "distinguished": null, "type": "comment", "score": 1, "id": "ekia4jm"}, {"created_at": 1554851215.0, "distinguished": null, "type": "comment", "score": 3, "id": "ekia1zw"}, {"created_at": 1554767031.0, "distinguished": null, "type": "comment", "score": 7, "id": "ekfih4v"}, {"created_at": 1554520828.0, "distinguished": null, "type": "comment", "score": 2, "id": "ek85hxq"}, {"created_at": 1553576153.0, "distinguished": null, "type": "comment", "score": 1, "id": "ejealxb"}, {"created_at": 1553431748.0, "distinguished": null, "type": "comment", "score": 0, "id": "ej9fx13"}, {"created_at": 1553388993.0, "distinguished": null, "type": "comment", "score": 1, "id": "ej8hqsp"}, {"created_at": 1553388122.0, "distinguished": null, "type": "comment", "score": 2, "id": "ej8gqnz"}, {"created_at": 1553233978.0, "distinguished": null, "type": "comment", "score": 7, "id": "ej3lh6t"}, {"created_at": 1553233878.0, "distinguished": null, "type": "comment", "score": 6, "id": "ej3leg7"}, {"created_at": 1553145617.0, "distinguished": null, "type": "comment", "score": 9, "id": "ej0o0bx"}, {"created_at": 1553120903.0, "distinguished": null, "type": "comment", "score": 7, "id": "eizt09h"}], "id": "nba"}, {"post_data": [{"created_at": 1555457094.0, "distinguished": null, "type": "comment", "score": 1, "id": "el26nve"}, {"created_at": 1555457063.0, "distinguished": null, "type": "comment", "score": 1, "id": "el26mf6"}, {"created_at": 1555456757.0, "distinguished": null, "type": "comment", "score": 0, "id": "el267o0"}, {"created_at": 1554969284.0, "distinguished": null, "type": "comment", "score": 2, "id": "ekm3i9v"}, {"created_at": 1554968013.0, "distinguished": null, "type": "comment", "score": 2, "id": "ekm2m5f"}, {"created_at": 1554875649.0, "distinguished": null, "type": "comment", "score": 2, "id": "ekj2qge"}, {"created_at": 1554104255.0, "distinguished": null, "type": "comment", "score": 1, "id": "ejv0dn5"}, {"created_at": 1552581305.0, "distinguished": null, "type": "comment", "score": 1, "id": "eiiqxyq"}, {"created_at": 1552581248.0, "distinguished": null, "type": "comment", "score": 1, "id": "eiiquqd"}, {"created_at": 1552580933.0, "distinguished": null, "type": "comment", "score": 1, "id": "eiiqcze"}, {"created_at": 1552580630.0, "distinguished": null, "type": "comment", "score": 1, "id": "eiipvr0"}, {"created_at": 1552580050.0, "distinguished": null, "type": "comment", "score": 5, "id": "eiioyw3"}, {"created_at": 1552579150.0, "distinguished": null, "type": "comment", "score": 1, "id": "eiinkax"}, {"created_at": 1552561341.0, "distinguished": null, "type": "comment", "score": 1, "id": "eii0rw7"}, {"created_at": 1552561246.0, "distinguished": null, "type": "comment", "score": 1, "id": "eii0ols"}, {"created_at": 1552196267.0, "distinguished": null, "type": "comment", "score": 1, "id": "ei6vwvf"}, {"created_at": 1552025752.0, "distinguished": null, "type": "comment", "score": 5, "id": "ei1xt31"}, {"created_at": 1549345194.0, "distinguished": null, "type": "comment", "score": 2, "id": "efs1ron"}], "id": "FIFA"}, {"post_data": [{"created_at": 1554955704.0, "distinguished": null, "type": "comment", "score": 2, "id": "ekltsw7"}], "id": "OrlandoMagic"}, {"post_data": [{"created_at": 1554343137.0, "distinguished": null, "type": "comment", "score": 1, "id": "ek2m4lp"}, {"created_at": 1554342762.0, "distinguished": null, "type": "comment", "score": -7, "id": "ek2lntu"}], "id": "GoNets"}, {"post_data": [{"created_at": 1551498858.0, "distinguished": null, "type": "comment", "score": 7, "id": "ehlswhb"}], "id": "ripcity"}, {"post_data": [{"created_at": 1551241054.0, "distinguished": null, "type": "comment", "score": 1, "id": "ehdgi61"}, {"created_at": 1551151772.0, "distinguished": null, "type": "comment", "score": 5, "id": "ehaoe3j"}, {"created_at": 1549537065.0, "distinguished": null, "type": "submission", "score": 3, "id": "ao2lct"}], "id": "UCalgary"}, {"post_data": [{"created_at": 1551235882.0, "distinguished": null, "type": "comment", "score": 0, "id": "ehda2vz"}], "id": "bostonceltics"}, {"post_data": [{"created_at": 1549535851.0, "distinguished": null, "type": "comment", "score": 6, "id": "efxp4hg"}, {"created_at": 1509354186.0, "distinguished": null, "type": "comment", "score": 2, "id": "dp34wlh"}], "id": "uAlberta"}, {"post_data": [{"created_at": 1546755345.0, "distinguished": null, "type": "comment", "score": 26, "id": "edd3nni"}], "id": "MkeBucks"}, {"post_data": [{"created_at": 1525695667.0, "distinguished": null, "type": "comment", "score": 2, "id": "dykye33"}], "id": "FortNiteBR"}, {"post_data": [{"created_at": 1524698517.0, "distinguished": null, "type": "comment", "score": 1, "id": "dxyznuy"}], "id": "nbastreams"}, {"post_data": [{"created_at": 1509597289.0, "distinguished": null, "type": "comment", "score": 1, "id": "dp85qq9"}, {"created_at": 1509594337.0, "distinguished": null, "type": "comment", "score": 1, "id": "dp83i0b"}], "id": "ATT"}, {"post_data": [{"created_at": 1509477453.0, "distinguished": null, "type": "comment", "score": 1, "id": "dp5ml7i"}], "id": "iphone"}], "links": [{"time_delta": [1302.0, 3828.0, 1779.0, 133.0, 258.0, 149.0, 124.0, 297.0, 168.0, 225.0, 181.0, 42.0, 116.0, 462.0, 890.0, 70.0, 469.0, 167.0, 59.0, 42.0, 39.0, 145.0, 49.0, 133.0, 424.0, 176.0, 175.0, 165.0, 142.0, 50.0, 104.0, 20.0, 203.0, 339.0, 128.0, 63.0, 191.0, 543.0, 405.0, 583.0, 96.0, 364.0, 130.0, 11908.0, 1136.0, 45939.0, 133.0, 542.0, 3603.0, 10865.0, 8316.0, 2874.0, 3754.0, 3149.0, 12802.0, 6059.0, 573.0, 5637.0, 1391.0, 445.0, 1532.0, 3919.0, 13548.0, 7007.0, 5499.0, 8113.0, 7551.0, 1150.0, 1736.0, 6770.0, 52151.0, 342.0, 363.0, 13543.0, 10686.0, 342.0, 103.0, 151.0, 250.0, 71.0, 204.0, 67.0, 70.0, 129.0, 73.0, 318.0, 592.0, 352.0, 188.0, 180.0, 61.0, 102.0, 95.0, 123.0, 1170.0, 114.0, 138.0, 574.0, 443.0, 372.0, 781.0, 345.0, 778.0, 700.0, 137.0, 87.0, 50.0, 165.0, 114.0, 473.0, 138.0, 8547.0, 421.0, 2273.0, 3575.0, 14864.0, 386.0, 510.0, 3927.0, 14207.0, 5636.0, 454.0, 15808.0, 2221.0, 741.0, 11626.0, 3656.0, 11354.0, 10362.0, 504.0, 10649.0, 324.0, 28495.0, 766.0, 2384.0, 221.0, 2932.0, 1914.0, 330.0, 7803.0, 242.0, 3337.0, 320.0, 12880.0, 881.0, 63.0, 526.0, 356.0, 114.0, 587.0, 59.0, 143.0, 241.0, 160.0, 91.0, 400.0, 210.0, 256.0, 81.0, 149.0, 281.0, 571.0, 174.0, 172.0, 211.0, 459.0, 53.0, 27499.0, 25188.0, 2742.0, 6772.0, 1998.0, 31.0, 44645.0, 6303.0, 2557.0, 2042.0, 5169.0, 19397.0, 702.0, 61.0, 2010.0, 31494.0, 380.0, 15375.0, 29742.0, 1860.0, 390.0, 104.0, 172.0, 285.0, 58.0, 284.0, 249.0, 816.0, 82.0, 51.0, 55.0, 392.0, 84.0, 285.0, 56.0, 66250.0, 493.0, 23602.0, 16102.0, 278.0, 12618.0, 1497.0, 775.0, 245.0, 2216.0, 534.0, 659.0, 146.0, 363.0, 710.0, 1325.0, 2184.0, 92095.0, 8952.0, 55179.0, 5024.0, 2348.0, 691.0, 1714.0, 1875.0, 5270.0, 16847.0, 19281.0, 17960.0, 5385.0, 48431.0, 7821.0, 98.0, 282.0, 68.0, 175.0, 148.0, 97.0, 2395.0, 106.0, 23.0, 59.0, 267.0, 358.0, 1508.0, 1346.0, 10197.0, 5180.0, 144972.0, 5721.0, 40631.0, 217.0, 46072.0, 86777.0, 39.0, 404.0, 118.0, 1021.0, 441.0, 321.0, 200.0, 553.0, 217.0, 912.0, 236.0, 7433.0, 23028.0, 39106.0, 61.0, 69304.0, 6357.0, 969.0, 311.0, 96.0, 120.0, 365.0, 489.0, 751.0, 426.0, 347.0, 226.0, 77.0, 111.0, 211.0, 983.0, 693.0, 115.0, 382.0, 116.0, 145.0, 83.0, 156.0, 417.0, 321.0, 96.0, 686.0, 188.0, 110.0, 74.0, 66.0, 142.0, 32.0, 1462.0, 993.0, 554.0, 626.0, 4857.0, 32314.0, 20111.0, 340.0, 5744.0, 966.0, 8980.0, 19183.0, 286.0, 3077.0, 20366.0, 9583.0, 235.0, 43.0, 250.0, 167.0, 52.0, 150.0, 182.0, 222.0, 107.0, 195.0, 36.0, 99.0, 57.0, 146.0, 279.0, 131.0, 226.0, 137.0, 95.0, 83.0, 189.0, 193.0, 413.0, 242.0, 118.0, 165.0, 181.0, 283.0, 200.0, 143.0, 144.0, 86.0, 51.0, 1070.0, 248.0, 133.0, 138.0, 39.0, 247.0, 36.0, 365.0, 108.0, 198.0, 63.0, 216.0, 164.0, 109.0, 40.0, 110.0, 140.0, 110.0, 100.0, 218.0, 80.0, 106.0, 52.0, 88.0, 62.0, 58.0, 71.0, 44.0, 63.0, 83.0, 97.0, 1175.0, 109.0, 3232.0, 38060.0, 59212.0, 944.0, 6812.0, 49255.0, 108.0, 1289.0, 306.0, 266.0, 27761.0, 6200.0, 1262.0, 1095.0, 618.0, 30118.0, 29921.0, 289.0, 310.0, 2602.0, 1362.0, 2030.0, 35.0, 166.0, 434.0, 117.0, 514.0, 9173.0, 176366.0, 849.0, 80854.0, 15553.0, 32329.0, 65805.0, 708.0, 791.0, 6114.0, 2074.0, 66533.0, 1307.0, 39.0, 195.0, 1357.0, 1259.0, 410.0, 81.0, 131.0, 2273.0, 67.0, 105.0, 101.0, 179.0, 116.0, 65832.0, 4883.0, 12569.0, 6159.0, 26919.0, 61126.0, 2209.0, 1280.0, 276.0, 91169.0, 416.0, 62534.0, 360.0, 1977.0, 5201.0, 56.0, 73261.0, 7488.0, 350.0, 2325.0, 292.0, 6565.0, 184704.0, 38953.0, 7344.0, 43198.0, 107568.0, 77.0, 182393.0, 347970.0, 84228.0, 43647.0, 1146.0, 29633.0, 83481.0, 146.0, 148679.0, 243.0, 274.0, 165895.0, 32918.0, 1612.0, 1457.0, 104.0, 194.0, 36.0, 644.0, 460.0, 1765.0, 646.0, 13521.0, 15662.0, 81341.0, 25228.0, 52609.0, 70844.0, 7333.0, 4081.0, 550606.0, 11960.0, 691355.0], "count": 500, "source": "torontoraptors", "target": "torontoraptors"}, {"time_delta": [12253.0, 9958.0, 9684.0, 500.0, 172.0, 441.0, 22980.0, 6195.0, 25492.0, 23522.0, 23454.0, 2997.0, 5825.0], "count": 13, "source": "torontoraptors", "target": "nba"}, {"time_delta": [4220.0, 6480.0, 14895.0, 7651.0, 217.0, 235.0, 169018.0, 95480.0, 6969.0, 223343.0], "count": 10, "source": "torontoraptors", "target": "FIFA"}, {"time_delta": [678.0], "count": 1, "source": "torontoraptors", "target": "OrlandoMagic"}, {"time_delta": [1465.0], "count": 1, "source": "torontoraptors", "target": "GoNets"}, {"time_delta": [983.0], "count": 1, "source": "torontoraptors", "target": "ripcity"}, {"time_delta": [3451.0], "count": 1, "source": "torontoraptors", "target": "bostonceltics"}, {"time_delta": [80276.0], "count": 1, "source": "torontoraptors", "target": "UCalgary"}, {"time_delta": [759.0], "count": 1, "source": "torontoraptors", "target": "uAlberta"}, {"time_delta": [4934395.0], "count": 1, "source": "torontoraptors", "target": "MkeBucks"}, {"time_delta": [8040.0, 34073.0, 9170.0, 385.0, 199.0, 3300.0, 19491.0, 61455.0, 847.0, 25395.0, 42984.0, 31495.0, 7245.0], "count": 13, "source": "nba", "target": "torontoraptors"}, {"time_delta": [811.0, 793.0, 54.0, 42755.0, 871.0, 100.0], "count": 6, "source": "nba", "target": "nba"}, {"time_delta": [1165.0, 5138.0, 48142.0, 36393.0, 5445.0, 86.0, 17574.0, 180408.0, 75035.0, 54146.0], "count": 10, "source": "FIFA", "target": "torontoraptors"}, {"time_delta": [31.0, 306.0, 1271.0, 57.0, 315.0, 580.0, 900.0, 95.0], "count": 8, "source": "FIFA", "target": "FIFA"}, {"time_delta": [2679.0], "count": 1, "source": "OrlandoMagic", "target": "torontoraptors"}, {"time_delta": [48790.0], "count": 1, "source": "GoNets", "target": "torontoraptors"}, {"time_delta": [375.0], "count": 1, "source": "GoNets", "target": "GoNets"}, {"time_delta": [242.0], "count": 1, "source": "ripcity", "target": "torontoraptors"}, {"time_delta": [170815.0, 71127.0, 25016.0], "count": 3, "source": "UCalgary", "target": "torontoraptors"}, {"time_delta": [5172.0], "count": 1, "source": "bostonceltics", "target": "UCalgary"}, {"time_delta": [1214.0], "count": 1, "source": "uAlberta", "target": "UCalgary"}, {"time_delta": [123267.0], "count": 1, "source": "uAlberta", "target": "iphone"}, {"time_delta": [977718.0], "count": 1, "source": "MkeBucks", "target": "torontoraptors"}, {"time_delta": [16125283.0], "count": 1, "source": "FortNiteBR", "target": "torontoraptors"}, {"time_delta": [997150.0], "count": 1, "source": "nbastreams", "target": "FortNiteBR"}, {"time_delta": [15101228.0], "count": 1, "source": "ATT", "target": "nbastreams"}, {"time_delta": [2952.0], "count": 1, "source": "ATT", "target": "ATT"}, {"time_delta": [116884.0], "count": 1, "source": "iphone", "target": "ATT"}]}}