{"sort_type": "controversial_all", "subreddit": "crazyideas", "meta": {"created_at": 1454450442.0, "distinguished": null, "score": 0, "id": "43ub5c", "title": "Make Zelda a girl in the next Legend of Zelda game"}, "include_root": false, "graph": {"directed": true, "multigraph": false, "graph": {}, "nodes": [{"id": "594f3685c411e1a9a01c17974d990bda97e15fd1"}, {"id": "06de355098e3c501129b1f249b4c7b7b92ce6972"}], "links": [{"weight": 1, "meta": [{"score": 2, "edited": false, "created_utc": 1454444161.0, "id": "czldpb1"}], "source": "594f3685c411e1a9a01c17974d990bda97e15fd1", "target": "06de355098e3c501129b1f249b4c7b7b92ce6972"}, {"weight": 1, "meta": [{"score": 1, "edited": false, "created_utc": 1454446459.0, "id": "czlfg67"}], "source": "06de355098e3c501129b1f249b4c7b7b92ce6972", "target": "594f3685c411e1a9a01c17974d990bda97e15fd1"}]}}